{"1578": [{"qt": 1.0, "preco": 13.79, "doc": "FCL-SD025/167764", "data": "2025-10-14", "lote": "23304", "val": "2025-10-31", "desc": "Ovos Industria L Uli Cx 5 Dz"}, {"qt": 1.0, "preco": 13.79, "doc": "FCL-SD025/172003", "data": "2025-10-21", "lote": "23312", "val": "2025-11-08", "desc": "Ovos Industria L Uli Cx 5 Dz"}], "15945": [{"qt": 2.0, "preco": 4.69, "doc": "FCL-SD025/167764", "data": "2025-10-14", "lote": "255272", "val": "2025-11-13", "desc": "Fiambre Fatiado Uli 1,2 Kg"}], "15993": [{"qt": 4.0, "preco": 6.79, "doc": "FCL-SD025/172003", "data": "2025-10-21", "lote": "300925", "val": "2025-12-29", "desc": "Qj.Edam Fatiado Uli 1 kg"}], "16580": [{"qt": 2.507, "preco": 9.99, "doc": "FCL-SD025/167764", "data": "2025-10-14", "lote": "VC2591I", "val": "2025-12-25", "desc": "Qj. Flamengo Fatiado Limiano Kg"}], "5348": [{"qt": 1.0, "preco": 11.25, "doc": "FCL-SD025/167764", "data": "2025-10-14", "lote": "030019251140151", "val": "2027-04-30", "desc": "Mexilhao M/Concha N.Zelandia 30/40 Cx1Kg"}], "5672": [{"qt": 1.0, "preco": 27.29, "doc": "FCL-SD025/162162", "data": "2025-10-06", "lote": "0443825", "val": "2027-03-20", "desc": "Rissois De Carne Mini Uli Cx 200 Un"}], "7515": [{"qt": 1.0, "preco": 16.19, "doc": "FCL-SD025/172003", "data": "2025-10-21", "lote": "L5236", "val": "2027-09-30", "desc": "Arroz Agulha Cozinha Velha 12x1 Kg"}]}