{"1003": [{"qt": 2.7, "preco": 3.91, "doc": "FCL-BJ125/081133", "data": "2025-11-28", "lote": "F14831125", "val": "2025-12-01", "desc": "Frango Int.Fresco Avibom 800 Gr"}], "1204": [{"qt": 2.7, "preco": 3.69, "doc": "FCL-BJ126/018193", "data": "2026-04-01", "lote": "1400014417", "val": "2026-04-04", "desc": "Frango Int.Fresco Avicasal 900/1000 Gr"}, {"qt": 2.87, "preco": 3.69, "doc": "FCL-PT026/034210", "data": "2026-05-01", "lote": "1400014509", "val": "2026-05-07", "desc": "Frango Int.Fresco Avicasal 900/1000 Gr"}], "15444": [{"qt": 1.0, "preco": 14.32, "doc": "FCL-BJ125/069581", "data": "2025-10-07", "lote": "201525", "val": "2026-05-15", "desc": "Cheesecake F.Silvestres Cong.Uli Cx1,5Kg"}], "15462": [{"qt": 1.0, "preco": 8.99, "doc": "FCL-BJ125/074951", "data": "2025-11-07", "lote": "2604073033", "val": "2026-04-07", "desc": "Manteiga Doses C/Sal Mimosa 100x8 Gr"}, {"qt": 1.0, "preco": 8.99, "doc": "FCL-BJ126/005890", "data": "2026-01-27", "lote": "2607013039", "val": "2026-07-01", "desc": "Manteiga Doses C/Sal Mimosa 100x8 Gr"}, {"qt": 1.0, "preco": 8.99, "doc": "FCL-BJ126/018193", "data": "2026-04-01", "lote": "2608313035", "val": "2026-08-31", "desc": "Manteiga Doses C/Sal Mimosa 100x8 Gr"}, {"qt": 1.0, "preco": 8.99, "doc": "FCL-LS826/001872", "data": "2026-05-29", "lote": "2610273052", "val": "2026-10-27", "desc": "Manteiga Doses C/Sal Mimosa 100x8 Gr"}], "15690": [{"qt": 1.0, "preco": 20.34, "doc": "FCL-BJ126/005890", "data": "2026-01-27", "lote": "T01626LA", "val": "2027-02-11", "desc": "Caldeirada Peixe Cong. Cx 6 Kg"}, {"qt": 1.0, "preco": 22.99, "doc": "FCL-BJ126/012155", "data": "2026-02-27", "lote": "T04226JA", "val": "2027-03-31", "desc": "Caldeirada Peixe Cong. Cx 6 Kg"}], "1578": [{"qt": 2.0, "preco": 13.79, "doc": "FCL-BJ125/069581", "data": "2025-10-07", "lote": "23297", "val": "2025-10-24", "desc": "Ovos Industria L Uli Cx 5 Dz"}, {"qt": 1.0, "preco": 13.79, "doc": "FCL-BJ025/045322", "data": "2025-10-17", "lote": "23309", "val": "2025-11-05", "desc": "Ovos Industria L Uli Cx 5 Dz"}, {"qt": 1.0, "preco": 14.89, "doc": "FCL-BJ125/074951", "data": "2025-11-07", "lote": "23329", "val": "2025-11-25", "desc": "Ovos Industria L Uli Cx 5 Dz"}, {"qt": 1.0, "preco": 14.89, "doc": "FCL-BJ125/081133", "data": "2025-11-28", "lote": "23351", "val": "2025-12-17", "desc": "Ovos Industria L Uli Cx 5 Dz"}, {"qt": 1.0, "preco": 14.89, "doc": "FCL-BJ025/050797", "data": "2025-12-05", "lote": "23359", "val": "2025-12-25", "desc": "Ovos Industria L Uli Cx 5 Dz"}, {"qt": 1.0, "preco": 14.89, "doc": "FCL-BJ126/005890", "data": "2026-01-27", "lote": "326044", "val": "2026-02-13", "desc": "Ovos Industria L Uli Cx 5 Dz"}, {"qt": 1.0, "preco": 14.89, "doc": "FCL-BJ126/012155", "data": "2026-02-27", "lote": "326075", "val": "2026-03-16", "desc": "Ovos Industria L Uli Cx 5 Dz"}, {"qt": 1.0, "preco": 14.89, "doc": "FCL-BJ126/013627", "data": "2026-03-06", "lote": "326084", "val": "2026-03-25", "desc": "Ovos Industria L Uli Cx 5 Dz"}, {"qt": 1.0, "preco": 14.89, "doc": "FCL-LS126/001560", "data": "2026-05-01", "lote": "326129", "val": "2026-05-09", "desc": "Ovos Industria L Uli Cx 5 Dz"}, {"qt": 1.0, "preco": 14.89, "doc": "FCL-LS826/001872", "data": "2026-05-29", "lote": "326166", "val": "2026-06-15", "desc": "Ovos Industria L Uli Cx 5 Dz"}], "16630": [{"qt": 1.0, "preco": 7.15, "doc": "FCL-BJ025/050797", "data": "2025-12-05", "lote": "01032027", "val": "2027-03-01", "desc": "Caldo Carne Soluvel METRO Chef 1 kg"}], "1684": [{"qt": 9.38, "preco": 4.45, "doc": "FCL-BJ126/012155", "data": "2026-02-27", "lote": "528100000", "val": "2027-04-08", "desc": "Porco Tiras Entrecosto Cong.Rivasam"}, {"qt": 9.7, "preco": 4.75, "doc": "FCL-BJ126/013627", "data": "2026-03-06", "lote": "528100000", "val": "2027-04-08", "desc": "Porco Tiras Entrecosto Cong.Rivasam"}, {"qt": 9.64, "preco": 5.25, "doc": "FCL-BJ126/018193", "data": "2026-04-01", "lote": "528300000", "val": "2027-04-10", "desc": "Porco Tiras Entrecosto Cong.Rivasam"}, {"qt": 9.97, "preco": 5.25, "doc": "FCL-LX126/002857", "data": "2026-05-01", "lote": "602100000", "val": "2028-01-21", "desc": "Porco Tiras Entrecosto Cong.Rivasam"}], "16966": [{"qt": 5.5, "preco": 4.76, "doc": "FCL-BJ126/012155", "data": "2026-02-27", "lote": "0000000556", "val": "2026-03-02", "desc": "Pato Fresco C/Miudos Marinhave"}], "2966": [{"qt": 1.0, "preco": 91.35, "doc": "FCL-BJ126/013627", "data": "2026-03-06", "lote": "E020225315", "val": "2027-05-31", "desc": "Bac.Dem.P.C/Lom.Cong.300/400 Hig.Uli 5Kg"}], "3018": [{"qt": 1.0, "preco": 9.35, "doc": "FCL-BJ125/069581", "data": "2025-10-07", "lote": "L51640W098", "val": "2027-06-30", "desc": "Caldo Galinha Pasta Knorr Lt 1 Kg"}, {"qt": 1.0, "preco": 12.39, "doc": "FCL-LS126/001560", "data": "2026-05-01", "lote": "L60440W098", "val": "2028-02-28", "desc": "Caldo Galinha Pasta Knorr Lt 1 Kg"}], "3114": [{"qt": 1.0, "preco": 25.99, "doc": "FCL-BJ126/012155", "data": "2026-02-27", "lote": "SP325310109", "val": "2028-12-01", "desc": "Pate Sardinha Uli 100x22 Gr"}], "3208": [{"qt": 1.0, "preco": 13.95, "doc": "FCL-BJ125/069581", "data": "2025-10-07", "lote": "21A25", "val": "2027-08-31", "desc": "Massa Pimento Catalao Balde 5.7 Kg"}, {"qt": 1.0, "preco": 13.95, "doc": "FCL-BJ025/050797", "data": "2025-12-05", "lote": "26B25", "val": "2027-11-30", "desc": "Massa Pimento Catalao Balde 5.7 Kg"}, {"qt": 1.0, "preco": 13.95, "doc": "FCL-BJ126/012155", "data": "2026-02-27", "lote": "02A262600247", "val": "2028-01-01", "desc": "Massa Pimento Catalao Balde 5.7 Kg"}, {"qt": 1.0, "preco": 13.95, "doc": "FCL-LS126/001560", "data": "2026-05-01", "lote": "08A262602055", "val": "2028-03-31", "desc": "Massa Pimento Catalao Balde 5.7 Kg"}], "3487": [{"qt": 1.0, "preco": 19.89, "doc": "FCL-BJ125/069581", "data": "2025-10-07", "lote": "L5223833", "val": "2026-07-08", "desc": "Oleo Alimentar Fula 10 Lt."}, {"qt": 1.0, "preco": 19.89, "doc": "FCL-BJ025/045322", "data": "2025-10-17", "lote": "L5223833", "val": "2026-07-08", "desc": "Oleo Alimentar Fula 10 Lt."}, {"qt": 1.0, "preco": 19.15, "doc": "FCL-BJ125/074951", "data": "2025-11-07", "lote": "L5216333", "val": "2026-05-06", "desc": "Oleo Alimentar Fula 10 Lt."}, {"qt": 1.0, "preco": 18.65, "doc": "FCL-BJ025/050797", "data": "2025-12-05", "lote": "L5216833", "val": "2026-05-09", "desc": "Oleo Alimentar Fula 10 Lt."}, {"qt": 1.0, "preco": 18.65, "doc": "FCL-BJ125/088551", "data": "2025-12-31", "lote": "L5216833", "val": "2026-05-09", "desc": "Oleo Alimentar Fula 10 Lt."}, {"qt": 1.0, "preco": 17.99, "doc": "FCL-BJ126/005890", "data": "2026-01-27", "lote": "L5216833", "val": "2026-07-08", "desc": "Oleo Alimentar Fula 10 Lt."}, {"qt": 1.0, "preco": 17.99, "doc": "FCL-BJ126/012155", "data": "2026-02-27", "lote": "L5244933", "val": "2026-12-02", "desc": "Oleo Alimentar Fula 10 Lt."}, {"qt": 1.0, "preco": 17.99, "doc": "FCL-BJ126/013627", "data": "2026-03-06", "lote": "L5244933", "val": "2026-12-02", "desc": "Oleo Alimentar Fula 10 Lt."}, {"qt": 1.0, "preco": 17.99, "doc": "FCL-BJ126/018193", "data": "2026-04-01", "lote": "6207633", "val": "2027-02-13", "desc": "Oleo Alimentar Fula 10 Lt."}, {"qt": 1.0, "preco": 17.99, "doc": "FCL-LS126/001560", "data": "2026-05-01", "lote": "L6211233", "val": "2027-03-12", "desc": "Oleo Alimentar Fula 10 Lt."}, {"qt": 1.0, "preco": 17.99, "doc": "FCL-LS826/001872", "data": "2026-05-29", "lote": "L6209733", "val": "2027-03-03", "desc": "Oleo Alimentar Fula 10 Lt."}], "3733": [{"qt": 1.0, "preco": 6.35, "doc": "FCL-BJ125/069581", "data": "2025-10-07", "lote": "2224125", "val": "2026-08-31", "desc": "Pickles 4 Frutos Tremoceira Balde 4,8 Kg"}, {"qt": 1.0, "preco": 6.35, "doc": "FCL-BJ126/018193", "data": "2026-04-01", "lote": "2204326", "val": "2027-02-28", "desc": "Pickles 4 Frutos Tremoceira Balde 4,8 Kg"}, {"qt": 1.0, "preco": 6.35, "doc": "FCL-LS126/001560", "data": "2026-05-01", "lote": "2208526", "val": "2027-03-31", "desc": "Pickles 4 Frutos Tremoceira Balde 4,8 Kg"}], "5344": [{"qt": 1.0, "preco": 63.0, "doc": "FCL-BJ125/088551", "data": "2025-12-31", "lote": "T250602", "val": "2028-05-30", "desc": "Ameijoa-Japonesa Cong.40/60 6x1Kg"}, {"qt": 1.0, "preco": 66.0, "doc": "FCL-BJ126/013627", "data": "2026-03-06", "lote": "T250602", "val": "2028-05-30", "desc": "Ameijoa-Japonesa Cong.40/60 6x1Kg"}, {"qt": 1.0, "preco": 61.95, "doc": "FCL-LX926/001774", "data": "2026-05-29", "lote": "T250602", "val": "2028-05-30", "desc": "Ameijoa-Japonesa Cong.40/60 6x1Kg"}], "6084": [{"qt": 8.625, "preco": 16.29, "doc": "FCL-BJ125/088551", "data": "2025-12-31", "lote": "72189896", "val": "2026-01-20", "desc": "Nov.Vazia Fresca 8 Kg/+ Charal Vacuo"}], "61551": [{"qt": 4.93, "preco": 3.99, "doc": "FCL-BJ125/069581", "data": "2025-10-07", "lote": "051003841239", "val": "2026-09-10", "desc": "Porco Chispe Mao Aberto Cong.Uli Avulso"}, {"qt": 5.36, "preco": 3.99, "doc": "FCL-BJ126/012155", "data": "2026-02-27", "lote": "053503841239", "val": "2027-05-18", "desc": "Porco Chispe Mao Aberto Cong.Uli Avulso"}, {"qt": 5.169, "preco": 3.99, "doc": "FCL-LX126/002857", "data": "2026-05-01", "lote": "053463841239", "val": "2027-05-14", "desc": "Porco Chispe Mao Aberto Cong.Uli Avulso"}, {"qt": 6.52, "preco": 3.99, "doc": "FCL-LX926/001774", "data": "2026-05-29", "lote": "360795900044", "val": "2027-08-23", "desc": "Porco Chispe Mao Aberto Cong.Uli Avulso"}], "6264": [{"qt": 5.7, "preco": 6.56, "doc": "FCL-BJ125/069581", "data": "2025-10-07", "lote": "25035033", "val": "2025-10-09", "desc": "Porco Cachaco S/Osso Fresco"}, {"qt": 6.4, "preco": 5.58, "doc": "FCL-BJ125/081133", "data": "2025-11-28", "lote": "25048503", "val": "2025-11-30", "desc": "Porco Cachaco S/Osso Fresco"}, {"qt": 5.2, "preco": 5.39, "doc": "FCL-BJ126/012155", "data": "2026-02-27", "lote": "26071653", "val": "2026-03-01", "desc": "Porco Cachaco S/Osso Fresco"}, {"qt": 7.1, "preco": 5.59, "doc": "FCL-BJ126/013627", "data": "2026-03-06", "lote": "26074266", "val": "2026-03-10", "desc": "Porco Cachaco S/Osso Fresco"}, {"qt": 6.1, "preco": 5.99, "doc": "FCL-BJ126/018193", "data": "2026-04-01", "lote": "26080941", "val": "2026-04-05", "desc": "Porco Cachaco S/Osso Fresco"}], "6399": [{"qt": 1.0, "preco": 5.19, "doc": "FCL-BJ125/069581", "data": "2025-10-07", "lote": "180126", "val": "2026-01-18", "desc": "Leite Uht M/Gordo Agros Profission.6x1Lt"}, {"qt": 1.0, "preco": 5.19, "doc": "FCL-BJ125/074951", "data": "2025-11-07", "lote": "310326", "val": "2026-03-21", "desc": "Leite Uht M/Gordo Agros Profission.6x1Lt"}, {"qt": 2.0, "preco": 5.19, "doc": "FCL-BJ125/081133", "data": "2025-11-28", "lote": "030426", "val": "2026-04-04", "desc": "Leite Uht M/Gordo Agros Profission.6x1Lt"}, {"qt": 2.0, "preco": 5.19, "doc": "FCL-BJ125/088551", "data": "2025-12-31", "lote": "270426", "val": "2026-04-27", "desc": "Leite Uht M/Gordo Agros Profission.6x1Lt"}, {"qt": 2.0, "preco": 5.19, "doc": "FCL-BJ126/005890", "data": "2026-01-27", "lote": "220526", "val": "2026-05-22", "desc": "Leite Uht M/Gordo Agros Profission.6x1Lt"}], "66240": [{"qt": 4.649, "preco": 11.25, "doc": "FCL-BJ125/069581", "data": "2025-10-07", "lote": "352673790434", "val": "2025-10-22", "desc": "Nov.Aba S/Osso Fresca Nacional Vacuo Uli"}, {"qt": 11.258, "preco": 12.1, "doc": "FCL-BJ025/045322", "data": "2025-10-17", "lote": "052803590434", "val": "2025-11-03", "desc": "Nov.Aba S/Osso Fresca Nacional Vacuo Uli"}, {"qt": 3.934, "preco": 12.1, "doc": "FCL-BJ125/074951", "data": "2025-11-07", "lote": "352945330010", "val": "2025-11-17", "desc": "Nov.Aba S/Osso Fresca Nacional Vacuo Uli"}, {"qt": 2.674, "preco": 12.1, "doc": "FCL-BJ125/081133", "data": "2025-11-28", "lote": "053222920434", "val": "2025-12-15", "desc": "Nov.Aba S/Osso Fresca Nacional Vacuo Uli"}, {"qt": 13.038, "preco": 12.1, "doc": "FCL-BJ025/050797", "data": "2025-12-05", "lote": "353365330010", "val": "2025-12-29", "desc": "Nov.Aba S/Osso Fresca Nacional Vacuo Uli"}, {"qt": 6.234, "preco": 12.1, "doc": "FCL-BJ125/088551", "data": "2025-12-31", "lote": "053503100434", "val": "2026-01-12", "desc": "Nov.Aba S/Osso Fresca Nacional Vacuo Uli"}, {"qt": 3.714, "preco": 12.1, "doc": "FCL-BJ126/005890", "data": "2026-01-27", "lote": "060133100434", "val": "2026-02-09", "desc": "Nov.Aba S/Osso Fresca Nacional Vacuo Uli"}, {"qt": 9.754, "preco": 12.1, "doc": "FCL-BJ126/013627", "data": "2026-03-06", "lote": "060482920434", "val": "2026-03-16", "desc": "Nov.Aba S/Osso Fresca Nacional Vacuo Uli"}, {"qt": 9.054, "preco": 10.37, "doc": "FCL-BJ126/018193", "data": "2026-04-01", "lote": "060772420434", "val": "2026-04-14", "desc": "Nov.Aba S/Osso Fresca Nacional Vacuo Uli"}, {"qt": 5.264, "preco": 10.37, "doc": "FCL-PT026/044857", "data": "2026-05-29", "lote": "061402950434", "val": "2026-06-17", "desc": "Nov.Aba S/Osso Fresca Nacional Vacuo Uli"}], "7110": [{"qt": 7.575, "preco": 12.25, "doc": "FCL-BJ125/069581", "data": "2025-10-07", "lote": "040825ES", "val": "2026-08-04", "desc": "Nov.Osso Buck Fatiado Cong.Uli Hig."}, {"qt": 7.7, "preco": 12.25, "doc": "FCL-BJ126/018193", "data": "2026-04-01", "lote": "151225NL", "val": "2026-12-15", "desc": "Nov.Osso Buck Fatiado Cong.Uli Hig."}], "7227": [{"qt": 1.0, "preco": 53.99, "doc": "FCL-BJ125/069581", "data": "2025-10-07", "lote": "2253003", "val": "2027-07-23", "desc": "Porco Tira Entrecosto Cong Cx10 kg"}, {"qt": 1.0, "preco": 53.99, "doc": "FCL-BJ025/045322", "data": "2025-10-17", "lote": "2253003", "val": "2027-07-23", "desc": "Porco Tira Entrecosto Cong Cx10 kg"}, {"qt": 1.0, "preco": 53.99, "doc": "FCL-BJ125/074951", "data": "2025-11-07", "lote": "2253003", "val": "2027-07-23", "desc": "Porco Tira Entrecosto Cong Cx10 kg"}, {"qt": 1.0, "preco": 53.99, "doc": "FCL-BJ125/081133", "data": "2025-11-28", "lote": "2253005", "val": "2027-07-25", "desc": "Porco Tira Entrecosto Cong Cx10 kg"}, {"qt": 1.0, "preco": 49.99, "doc": "FCL-BJ126/005890", "data": "2026-01-27", "lote": "CIN515315", "val": "2027-06-20", "desc": "Porco Tira Entrecosto Cong Cx10 kg"}, {"qt": 1.0, "preco": 54.99, "doc": "FCL-LX926/001774", "data": "2026-05-29", "lote": "261702", "val": "2028-04-20", "desc": "Porco Tira Entrecosto Cong Cx10 kg"}], "7477": [{"qt": 1.542, "preco": 7.39, "doc": "FCL-BJ125/069581", "data": "2025-10-07", "lote": "25081518", "val": "2025-12-16", "desc": "Alheira Caca Topiteu Vacuo"}, {"qt": 1.68, "preco": 7.39, "doc": "FCL-BJ025/045322", "data": "2025-10-17", "lote": "25091111", "val": "2026-01-09", "desc": "Alheira Caca Topiteu Vacuo"}, {"qt": 1.694, "preco": 7.39, "doc": "FCL-BJ125/074951", "data": "2025-11-07", "lote": "25101617", "val": "2026-02-14", "desc": "Alheira Caca Topiteu Vacuo"}, {"qt": 1.732, "preco": 7.39, "doc": "FCL-BJ125/088551", "data": "2025-12-31", "lote": "25112803", "val": "2026-04-02", "desc": "Alheira Caca Topiteu Vacuo"}, {"qt": 1.596, "preco": 7.39, "doc": "FCL-BJ126/012155", "data": "2026-02-27", "lote": "26020409", "val": "2026-06-09", "desc": "Alheira Caca Topiteu Vacuo"}, {"qt": 1.622, "preco": 7.39, "doc": "FCL-BJ126/018193", "data": "2026-04-01", "lote": "26021316", "val": "2026-06-16", "desc": "Alheira Caca Topiteu Vacuo"}, {"qt": 1.626, "preco": 8.89, "doc": "FCL-LX126/002857", "data": "2026-05-01", "lote": "26032123", "val": "2026-07-21", "desc": "Alheira Caca Topiteu Vacuo"}, {"qt": 1.678, "preco": 8.89, "doc": "FCL-LX926/001774", "data": "2026-05-29", "lote": "26050811", "val": "2026-09-08", "desc": "Alheira Caca Topiteu Vacuo"}], "7773": [{"qt": 1.0, "preco": 12.69, "doc": "FCL-BJ126/005890", "data": "2026-01-27", "lote": "CF1218", "val": "2026-12-18", "desc": "Banha Porco Balde 4,7 Kg"}, {"qt": 1.0, "preco": 12.69, "doc": "FCL-BJ126/018193", "data": "2026-04-01", "lote": "CG0303", "val": "2027-03-03", "desc": "Banha Porco Balde 4,7 Kg"}, {"qt": 1.0, "preco": 12.69, "doc": "FCL-LS826/001872", "data": "2026-05-29", "lote": "CG0507", "val": "2027-05-07", "desc": "Banha Porco Balde 4,7 Kg"}], "78150": [{"qt": 3.144, "preco": 12.2, "doc": "FCL-PT026/034210", "data": "2026-05-01", "lote": "360985330013", "val": "2026-05-05", "desc": "Vitelao Aba S/Osso Fr Uli Vacuo"}], "8944": [{"qt": 1.0, "preco": 6.99, "doc": "FCL-BJ126/018193", "data": "2026-04-01", "lote": "9308669", "val": "2026-05-12", "desc": "Bacon Fatiado S/Courato Uli 3x350 Gr"}], "9146": [{"qt": 1.0, "preco": 5.65, "doc": "FCL-BJ125/069581", "data": "2025-10-07", "lote": "0783425", "val": "2030-08-20", "desc": "Sal Grosso Uli 20x1 Kg"}, {"qt": 1.0, "preco": 5.65, "doc": "FCL-BJ126/012155", "data": "2026-02-27", "lote": "0810426", "val": "2031-01-22", "desc": "Sal Grosso Uli 20x1 Kg"}, {"qt": 1.0, "preco": 5.65, "doc": "FCL-LS826/001872", "data": "2026-05-29", "lote": "0841926", "val": "2031-05-05", "desc": "Sal Grosso Uli 20x1 Kg"}]}