{"1143": [{"qt": 10.99, "preco": 3.65, "doc": "FCL-LS225/117402", "data": "2025-10-17", "lote": "Q34061025", "val": "2027-03-28", "desc": "Pato C/Miudos Cong. Avibom"}], "1240": [{"qt": 2.0, "preco": 24.49, "doc": "FCL-LS225/136037", "data": "2025-11-07", "lote": "520109000", "val": "2026-11-02", "desc": "Frango Perna C/Costas Cong.A IQF Cx10 Kg"}, {"qt": 3.0, "preco": 23.49, "doc": "FCL-LX226/019827", "data": "2026-02-27", "lote": "5350090000", "val": "2027-06-16", "desc": "Frango Perna C/Costas Cong.A IQF Cx10 Kg"}], "1251": [{"qt": 5.0, "preco": 24.49, "doc": "FCL-LS225/104497", "data": "2025-10-03", "lote": "000146990389", "val": "2026-08-10", "desc": "Frango Cotos Cong. A IQF Cx 10kg"}, {"qt": 2.0, "preco": 24.49, "doc": "FCL-LS225/117402", "data": "2025-10-17", "lote": "5227090000", "val": "2027-02-15", "desc": "Frango Cotos Cong. A IQF Cx 10kg"}, {"qt": 2.0, "preco": 24.49, "doc": "FCL-LS225/136037", "data": "2025-11-07", "lote": "5265092000", "val": "2027-03-23", "desc": "Frango Cotos Cong. A IQF Cx 10kg"}, {"qt": 3.0, "preco": 23.49, "doc": "FCL-LX226/019827", "data": "2026-02-27", "lote": "5263090000", "val": "2027-03-20", "desc": "Frango Cotos Cong. A IQF Cx 10kg"}], "15768": [{"qt": 1.0, "preco": 54.89, "doc": "FCL-LX226/019827", "data": "2026-02-27", "lote": "ND006102592972", "val": "2027-10-06", "desc": "Choco Int.Cong.200/300gr Cx 7 Kg"}], "16081": [{"qt": 17.27, "preco": 10.35, "doc": "FCL-LS326/001858", "data": "2026-01-09", "lote": "20250318C", "val": "2027-11-04", "desc": "Bovino Maminha Cong. Vacuo"}, {"qt": 21.62, "preco": 10.39, "doc": "FCL-LX226/026499", "data": "2026-03-07", "lote": "20250321", "val": "2028-11-26", "desc": "Bovino Maminha Cong. Vacuo"}, {"qt": 12.15, "preco": 10.85, "doc": "FCL-LX226/058698", "data": "2026-05-07", "lote": "132622114", "val": "2027-09-28", "desc": "Bovino Maminha Cong. Vacuo"}, {"qt": -12.15, "preco": 10.85, "doc": "NCC-LX026/003759", "data": "2026-05-14", "lote": "132622114", "val": "2027-09-28", "desc": "Bovino Maminha Cong. Vacuo"}], "16417": [{"qt": 15.6, "preco": 3.89, "doc": "FCL-LS225/159074", "data": "2025-12-05", "lote": "2061201090", "val": "2026-06-15", "desc": "Pato C/Miudos Cong.Hungria Vacuo"}, {"qt": 13.8, "preco": 4.22, "doc": "FCL-LX226/026499", "data": "2026-03-07", "lote": "25445412", "val": "2027-09-30", "desc": "Pato C/Miudos Cong.Hungria Vacuo"}], "16738": [{"qt": 1.0, "preco": 67.8, "doc": "FCL-LS225/104497", "data": "2025-10-03", "lote": "F31", "val": "2026-07-23", "desc": "Frango Peito C/Sal Cong.Ucrania 6x2 Kg"}, {"qt": 1.0, "preco": 69.89, "doc": "FCL-LS225/117402", "data": "2025-10-17", "lote": "F31", "val": "2026-07-23", "desc": "Frango Peito C/Sal Cong.Ucrania 6x2 Kg"}, {"qt": 1.0, "preco": 69.99, "doc": "FCL-LS225/136037", "data": "2025-11-07", "lote": "F55", "val": "2027-03-29", "desc": "Frango Peito C/Sal Cong.Ucrania 6x2 Kg"}, {"qt": 1.0, "preco": 61.08, "doc": "FCL-LX226/019827", "data": "2026-02-27", "lote": "F50", "val": "2027-03-23", "desc": "Frango Peito C/Sal Cong.Ucrania 6x2 Kg"}], "2666": [{"qt": 1.0, "preco": 49.3, "doc": "FCL-LX226/026499", "data": "2026-03-07", "lote": "NF-TS2501", "val": "2027-12-01", "desc": "Polpa Maracuja C/ Sementes Cong.10x500Gr"}], "4138": [{"qt": 6.0, "preco": 7.39, "doc": "FCL-LS226/033822", "data": "2026-05-07", "lote": "150926", "val": "2026-09-15", "desc": "Nata Acucarada.Spray UHT Debic 700 Ml"}, {"qt": -6.0, "preco": 7.39, "doc": "NCC-LS026/002765", "data": "2026-05-14", "lote": null, "val": null, "desc": "Nata Acucarada.Spray UHT Debic 700 Ml"}], "5663": [{"qt": 4.0, "preco": 16.95, "doc": "FCL-LS225/104497", "data": "2025-10-03", "lote": "1326", "val": "2026-08-27", "desc": "Pasteis Bacalhau Cong Snack Uli Cx 50 Un"}], "6004": [{"qt": 22.54, "preco": 7.89, "doc": "FCL-LS225/104497", "data": "2025-10-03", "lote": "25LS0022211H", "val": "2028-02-24", "desc": "Borrego Dianteiros Cong.N.Zelandia"}, {"qt": 2.848, "preco": 7.89, "doc": "FCL-LS225/136037", "data": "2025-11-07", "lote": "25LS0022211H", "val": "2028-02-24", "desc": "Borrego Dianteiros Cong.N.Zelandia"}, {"qt": 24.38, "preco": 7.89, "doc": "FCL-LS125/073698", "data": "2025-11-11", "lote": "25LS0022229J", "val": "2028-05-26", "desc": "Borrego Dianteiros Cong.N.Zelandia"}, {"qt": 1.0, "preco": 7.89, "doc": "FCL-LS225/139250", "data": "2025-11-11", "lote": "25LS0022229J", "val": "2028-05-26", "desc": "Borrego Dianteiros Cong.N.Zelandia"}, {"qt": 21.78, "preco": 7.89, "doc": "FCL-LS225/159074", "data": "2025-12-05", "lote": "25LS0022220K", "val": "2028-05-02", "desc": "Borrego Dianteiros Cong.N.Zelandia"}, {"qt": 22.58, "preco": 8.39, "doc": "FCL-LX226/003168", "data": "2026-02-06", "lote": "26LS2033527A", "val": "2028-01-25", "desc": "Borrego Dianteiros Cong.N.Zelandia"}, {"qt": -22.58, "preco": 0.4, "doc": "NCC-LX126/000315", "data": "2026-02-12", "lote": null, "val": null, "desc": "Borrego Dianteiros Cong.N.Zelandia"}, {"qt": 18.49, "preco": 7.95, "doc": "FCL-LX226/026499", "data": "2026-03-07", "lote": "26LS2033504C", "val": "2028-03-13", "desc": "Borrego Dianteiros Cong.N.Zelandia"}], "6122": [{"qt": 16.995, "preco": 12.79, "doc": "FCL-LS225/159074", "data": "2025-12-05", "lote": "330402", "val": "2027-11-27", "desc": "Cabrito Inteiro Franca Cong.4/8 Kg"}], "8485": [{"qt": 12.335, "preco": 7.05, "doc": "FCL-LS225/104497", "data": "2025-10-03", "lote": "0252601", "val": "2027-06-23", "desc": "Porco Bochecha Interna S/Osso Cong.Vacuo"}, {"qt": 10.0, "preco": 7.05, "doc": "FCL-LS225/117402", "data": "2025-10-17", "lote": "0252601", "val": "2027-06-23", "desc": "Porco Bochecha Interna S/Osso Cong.Vacuo"}]}