{"15268": [{"qt": 1.0, "preco": 35.2, "doc": "FCL-LS225/178067", "data": "2025-12-30", "lote": "1321S", "val": "2026-11-17", "desc": "Empada Galinha Med.Cong.+/- 80Gr Cx 50Un"}, {"qt": 1.0, "preco": 35.2, "doc": "FCL-LS226/015124", "data": "2026-01-22", "lote": "4324S", "val": "2026-11-20", "desc": "Empada Galinha Med.Cong.+/- 80Gr Cx 50Un"}, {"qt": 1.0, "preco": 36.65, "doc": "FCL-LX226/002546", "data": "2026-02-05", "lote": "5332S", "val": "2026-12-28", "desc": "Empada Galinha Med.Cong.+/- 80Gr Cx 50Un"}, {"qt": 1.0, "preco": 34.65, "doc": "FCL-LX226/039161", "data": "2026-03-28", "lote": "4057S", "val": "2027-02-26", "desc": "Empada Galinha Med.Cong.+/- 80Gr Cx 50Un"}], "1710": [{"qt": 1.0, "preco": 28.55, "doc": "FCL-LS225/178067", "data": "2025-12-30", "lote": "2144825", "val": "2027-05-29", "desc": "Rolinhos Queijo/Fiambre Cong.Uli Cx 50Un"}, {"qt": 1.0, "preco": 27.9, "doc": "FCL-LS326/001058", "data": "2026-01-08", "lote": "2144925", "val": "2027-06-05", "desc": "Rolinhos Queijo/Fiambre Cong.Uli Cx 50Un"}, {"qt": 1.0, "preco": 28.55, "doc": "FCL-LS226/015124", "data": "2026-01-22", "lote": "2140226", "val": "2027-07-10", "desc": "Rolinhos Queijo/Fiambre Cong.Uli Cx 50Un"}, {"qt": 1.0, "preco": 28.55, "doc": "FCL-LX226/002546", "data": "2026-02-05", "lote": "2150526", "val": "2027-08-01", "desc": "Rolinhos Queijo/Fiambre Cong.Uli Cx 50Un"}, {"qt": 1.0, "preco": 28.55, "doc": "FCL-LX226/012922", "data": "2026-02-19", "lote": "2150526", "val": "2027-08-01", "desc": "Rolinhos Queijo/Fiambre Cong.Uli Cx 50Un"}, {"qt": 1.0, "preco": 28.55, "doc": "FCL-LX226/030062", "data": "2026-03-12", "lote": "2130826", "val": "2027-08-20", "desc": "Rolinhos Queijo/Fiambre Cong.Uli Cx 50Un"}, {"qt": 1.0, "preco": 28.55, "doc": "FCL-LX226/039161", "data": "2026-03-28", "lote": "2150926", "val": "2027-08-29", "desc": "Rolinhos Queijo/Fiambre Cong.Uli Cx 50Un"}], "3498": [{"qt": 6.0, "preco": 16.27, "doc": "FCL-LS225/134839", "data": "2025-11-06", "lote": "L5214533", "val": "2026-04-22", "desc": "Oleo Alimentar Frigi 10 Lt."}, {"qt": 4.0, "preco": 16.27, "doc": "FCL-LS225/134839", "data": "2025-11-06", "lote": "L5214533", "val": "2026-04-22", "desc": "Oleo Alimentar Frigi 10 Lt."}, {"qt": 6.0, "preco": 16.49, "doc": "FCL-LS225/152051", "data": "2025-11-27", "lote": "L5211933", "val": "2026-03-31", "desc": "Oleo Alimentar Frigi 10 Lt."}, {"qt": 4.0, "preco": 16.49, "doc": "FCL-LS225/152051", "data": "2025-11-27", "lote": "L5211933", "val": "2026-03-31", "desc": "Oleo Alimentar Frigi 10 Lt."}, {"qt": 6.0, "preco": 14.99, "doc": "FCL-LS225/164460", "data": "2025-12-11", "lote": "L5211933", "val": "2026-03-31", "desc": "Oleo Alimentar Frigi 10 Lt."}, {"qt": 4.0, "preco": 14.99, "doc": "FCL-LS225/164460", "data": "2025-12-11", "lote": "L5211933", "val": "2026-03-31", "desc": "Oleo Alimentar Frigi 10 Lt."}, {"qt": 10.0, "preco": 13.89, "doc": "FCL-LS225/170632", "data": "2025-12-18", "lote": "L5214533", "val": "2026-04-22", "desc": "Oleo Alimentar Frigi 10 Lt."}, {"qt": 6.0, "preco": 14.99, "doc": "FCL-LX226/002546", "data": "2026-02-05", "lote": "L5215733", "val": "2026-04-30", "desc": "Oleo Alimentar Frigi 10 Lt."}, {"qt": 6.0, "preco": 14.99, "doc": "FCL-LX226/012922", "data": "2026-02-19", "lote": "L5217133", "val": "2026-05-13", "desc": "Oleo Alimentar Frigi 10 Lt."}, {"qt": 6.0, "preco": 14.99, "doc": "FCL-LX226/030062", "data": "2026-03-12", "lote": "L5217133", "val": "2026-05-13", "desc": "Oleo Alimentar Frigi 10 Lt."}, {"qt": 6.0, "preco": 15.99, "doc": "FCL-LX226/039161", "data": "2026-03-28", "lote": "L5219033", "val": "2026-05-27", "desc": "Oleo Alimentar Frigi 10 Lt."}], "50350": [{"qt": 0.955, "preco": 12.75, "doc": "FCL-LS225/178067", "data": "2025-12-30", "lote": "24425R", "val": "2027-09-30", "desc": "Sapateira Cong. Escocia 800/+ Vacuo"}], "5329": [{"qt": 1.0, "preco": 19.15, "doc": "FCL-LS225/178067", "data": "2025-12-30", "lote": "L5336", "val": "2027-06-30", "desc": "Bocas Sapateira Coz.Cong.12-20 Saco 1 kg"}], "5650": [{"qt": 1.0, "preco": 23.35, "doc": "FCL-LS226/015124", "data": "2026-01-22", "lote": "0954825", "val": "2027-05-30", "desc": "Rolinhos Salsicha Cong.Uli Cx 50 Un"}, {"qt": 1.0, "preco": 23.35, "doc": "FCL-LX226/002546", "data": "2026-02-05", "lote": "0950226", "val": "2027-07-11", "desc": "Rolinhos Salsicha Cong.Uli Cx 50 Un"}, {"qt": 1.0, "preco": 23.35, "doc": "FCL-LX226/030062", "data": "2026-03-12", "lote": "0960926", "val": "2027-08-30", "desc": "Rolinhos Salsicha Cong.Uli Cx 50 Un"}], "5653": [{"qt": 1.0, "preco": 32.1, "doc": "FCL-LS326/001058", "data": "2026-01-08", "lote": "2244625", "val": "2026-11-13", "desc": "Rissois Leitao Gr Cong.Uli Cx de 50 Un"}, {"qt": 2.0, "preco": 33.09, "doc": "FCL-LS226/015124", "data": "2026-01-22", "lote": "2245025", "val": "2026-12-11", "desc": "Rissois Leitao Gr Cong.Uli Cx de 50 Un"}, {"qt": 2.0, "preco": 33.09, "doc": "FCL-LX226/012922", "data": "2026-02-19", "lote": "2240226", "val": "2027-01-08", "desc": "Rissois Leitao Gr Cong.Uli Cx de 50 Un"}], "5655": [{"qt": 1.0, "preco": 22.79, "doc": "FCL-LX226/002546", "data": "2026-02-05", "lote": "0354525", "val": "2027-05-09", "desc": "Coxas De Frango Cong.Uli Cx 50 Un"}], "5656": [{"qt": 1.0, "preco": 19.99, "doc": "FCL-LS225/178067", "data": "2025-12-30", "lote": "2524825", "val": "2027-05-27", "desc": "Croquetes Carne Gr.Cong.Uli Cx 50 Un"}], "5657": [{"qt": 1.0, "preco": 19.75, "doc": "FCL-LS225/178067", "data": "2025-12-30", "lote": "0114625", "val": "2027-05-12", "desc": "Rissois Camarao Gr.Cong.Uli Cx 50 Un"}, {"qt": 1.0, "preco": 17.75, "doc": "FCL-LS326/001058", "data": "2026-01-08", "lote": "0124525", "val": "2027-05-06", "desc": "Rissois Camarao Gr.Cong.Uli Cx 50 Un"}, {"qt": 1.0, "preco": 19.75, "doc": "FCL-LX226/002546", "data": "2026-02-05", "lote": "0135025", "val": "2027-06-11", "desc": "Rissois Camarao Gr.Cong.Uli Cx 50 Un"}, {"qt": 1.0, "preco": 19.75, "doc": "FCL-LX226/012922", "data": "2026-02-19", "lote": "0115125", "val": "2027-06-16", "desc": "Rissois Camarao Gr.Cong.Uli Cx 50 Un"}, {"qt": 1.0, "preco": 19.75, "doc": "FCL-LX226/030062", "data": "2026-03-12", "lote": "0130526", "val": "2027-07-30", "desc": "Rissois Camarao Gr.Cong.Uli Cx 50 Un"}, {"qt": 1.0, "preco": 19.75, "doc": "FCL-LX226/039161", "data": "2026-03-28", "lote": "0130526", "val": "2027-07-30", "desc": "Rissois Camarao Gr.Cong.Uli Cx 50 Un"}], "5898": [{"qt": 1.0, "preco": 8.95, "doc": "FCL-LS326/001058", "data": "2026-01-08", "lote": "25205", "val": "2027-05-28", "desc": "Carne Sapateira Castanha Cong. Cov.500Gr"}], "8685": [{"qt": 6.0, "preco": 16.35, "doc": "FCL-LS225/109700", "data": "2025-10-09", "lote": "5228133", "val": "2026-08-11", "desc": "Oleo Alimentar Uli 10 Lt"}, {"qt": 6.0, "preco": 16.35, "doc": "FCL-LS225/122122", "data": "2025-10-23", "lote": "5227433", "val": "2026-08-06", "desc": "Oleo Alimentar Uli 10 Lt"}]}