{"1378": [{"qt": -3.0, "preco": 36.15, "doc": "NCC-LS025/004167", "data": "2025-10-02", "lote": "88725", "val": "2026-09-10", "desc": "Frango Bife Panado Cong.Uli Cx 4 Kg"}, {"qt": 1.0, "preco": 35.25, "doc": "FCL-LS225/108953", "data": "2025-10-08", "lote": "88725", "val": "2026-09-10", "desc": "Frango Bife Panado Cong.Uli Cx 4 Kg"}, {"qt": 1.0, "preco": 35.25, "doc": "FCL-LS225/125051", "data": "2025-10-27", "lote": "100325", "val": "2026-10-14", "desc": "Frango Bife Panado Cong.Uli Cx 4 Kg"}, {"qt": 1.0, "preco": 35.25, "doc": "FCL-LS225/143122", "data": "2025-11-17", "lote": "105125", "val": "2026-10-28", "desc": "Frango Bife Panado Cong.Uli Cx 4 Kg"}, {"qt": 1.0, "preco": 36.15, "doc": "FCL-LS225/166849", "data": "2025-12-15", "lote": "107125", "val": "2026-11-04", "desc": "Frango Bife Panado Cong.Uli Cx 4 Kg"}, {"qt": 1.0, "preco": 36.15, "doc": "FCL-LS226/011239", "data": "2026-01-16", "lote": "117825", "val": "2026-12-10", "desc": "Frango Bife Panado Cong.Uli Cx 4 Kg"}, {"qt": 1.0, "preco": 36.15, "doc": "FCL-LX226/056906", "data": "2026-05-04", "lote": "34626", "val": "2027-04-22", "desc": "Frango Bife Panado Cong.Uli Cx 4 Kg"}], "1397": [{"qt": 3.0, "preco": 19.45, "doc": "FCL-LS225/108953", "data": "2025-10-08", "lote": "25170", "val": "2026-12-19", "desc": "Panados Frango Cong.Eurofri.Cx4,76Kg"}, {"qt": 1.0, "preco": 19.45, "doc": "FCL-LS225/115082", "data": "2025-10-15", "lote": "25170", "val": "2026-12-19", "desc": "Panados Frango Cong.Eurofri.Cx4,76Kg"}, {"qt": 1.0, "preco": 19.45, "doc": "FCL-LS225/118973", "data": "2025-10-20", "lote": "25170", "val": "2026-12-19", "desc": "Panados Frango Cong.Eurofri.Cx4,76Kg"}, {"qt": 2.0, "preco": 19.45, "doc": "FCL-LS325/039527", "data": "2025-10-30", "lote": "25170", "val": "2026-12-19", "desc": "Panados Frango Cong.Eurofri.Cx4,76Kg"}, {"qt": 1.0, "preco": 19.45, "doc": "FCL-LS225/134992", "data": "2025-11-06", "lote": "25170", "val": "2026-12-19", "desc": "Panados Frango Cong.Eurofri.Cx4,76Kg"}, {"qt": 2.0, "preco": 19.45, "doc": "FCL-LS225/143122", "data": "2025-11-17", "lote": "25170", "val": "2026-12-19", "desc": "Panados Frango Cong.Eurofri.Cx4,76Kg"}, {"qt": 2.0, "preco": 19.45, "doc": "FCL-LS225/148949", "data": "2025-11-24", "lote": "25170", "val": "2026-12-19", "desc": "Panados Frango Cong.Eurofri.Cx4,76Kg"}, {"qt": 1.0, "preco": 21.25, "doc": "FCL-LS225/155040", "data": "2025-12-01", "lote": "25170", "val": "2026-12-19", "desc": "Panados Frango Cong.Eurofri.Cx4,76Kg"}, {"qt": 1.0, "preco": 21.25, "doc": "FCL-LS225/166849", "data": "2025-12-15", "lote": "25308", "val": "2027-05-04", "desc": "Panados Frango Cong.Eurofri.Cx4,76Kg"}, {"qt": 2.0, "preco": 21.25, "doc": "FCL-LS226/011239", "data": "2026-01-16", "lote": "25308", "val": "2027-05-04", "desc": "Panados Frango Cong.Eurofri.Cx4,76Kg"}, {"qt": 3.0, "preco": 21.25, "doc": "FCL-LS226/019351", "data": "2026-01-28", "lote": "25308", "val": "2027-05-04", "desc": "Panados Frango Cong.Eurofri.Cx4,76Kg"}, {"qt": 3.0, "preco": 21.25, "doc": "FCL-LX226/005597", "data": "2026-02-10", "lote": "25308", "val": "2027-05-04", "desc": "Panados Frango Cong.Eurofri.Cx4,76Kg"}, {"qt": 1.0, "preco": 21.25, "doc": "FCL-LX226/021616", "data": "2026-03-02", "lote": "25308", "val": "2027-05-04", "desc": "Panados Frango Cong.Eurofri.Cx4,76Kg"}, {"qt": 3.0, "preco": 21.25, "doc": "FCL-LX226/028293", "data": "2026-03-10", "lote": "25308", "val": "2027-05-04", "desc": "Panados Frango Cong.Eurofri.Cx4,76Kg"}, {"qt": 2.0, "preco": 21.25, "doc": "FCL-LX226/035631", "data": "2026-03-20", "lote": "25308", "val": "2027-05-04", "desc": "Panados Frango Cong.Eurofri.Cx4,76Kg"}, {"qt": 1.0, "preco": 21.25, "doc": "FCL-LX226/043361", "data": "2026-04-06", "lote": "25308", "val": "2027-05-04", "desc": "Panados Frango Cong.Eurofri.Cx4,76Kg"}, {"qt": 3.0, "preco": 21.25, "doc": "FCL-LX226/050014", "data": "2026-04-20", "lote": "25336", "val": "2027-06-02", "desc": "Panados Frango Cong.Eurofri.Cx4,76Kg"}, {"qt": 1.0, "preco": 21.25, "doc": "FCL-LX326/019753", "data": "2026-04-23", "lote": "25308", "val": "2027-05-04", "desc": "Panados Frango Cong.Eurofri.Cx4,76Kg"}, {"qt": 4.0, "preco": 21.25, "doc": "FCL-LX626/003192", "data": "2026-05-07", "lote": "25336", "val": "2027-06-02", "desc": "Panados Frango Cong.Eurofri.Cx4,76Kg"}, {"qt": 3.0, "preco": 21.25, "doc": "FCL-LX626/006357", "data": "2026-05-22", "lote": "26071", "val": "2027-09-12", "desc": "Panados Frango Cong.Eurofri.Cx4,76Kg"}, {"qt": 1.0, "preco": 21.25, "doc": "FCL-LX626/007325", "data": "2026-05-29", "lote": "26071", "val": "2027-09-12", "desc": "Panados Frango Cong.Eurofri.Cx4,76Kg"}, {"qt": 4.0, "preco": 21.25, "doc": "FCL-LX326/027773", "data": "2026-06-12", "lote": "26071", "val": "2027-09-12", "desc": "Panados Frango Cong.Eurofri.Cx4,76Kg"}], "1445": [{"qt": 1.0, "preco": 33.95, "doc": "FCL-LS226/019351", "data": "2026-01-28", "lote": "01142262", "val": "2027-06-02", "desc": "Frango Bife Panado Cong.Hig.Uli Cx 4 Kg"}, {"qt": 1.0, "preco": 33.95, "doc": "FCL-LX226/035631", "data": "2026-03-20", "lote": "01142373", "val": "2027-06-09", "desc": "Frango Bife Panado Cong.Hig.Uli Cx 4 Kg"}, {"qt": 1.0, "preco": 33.95, "doc": "FCL-LX626/006357", "data": "2026-05-22", "lote": "01144015", "val": "2027-09-28", "desc": "Frango Bife Panado Cong.Hig.Uli Cx 4 Kg"}], "15615": [{"qt": 1.0, "preco": 27.95, "doc": "FCL-LS225/129106", "data": "2025-10-31", "lote": "555", "val": "2026-04-29", "desc": "Pao Hamb. Cong. Bimbo 76x10 Cm +/- 55 Gr"}, {"qt": 2.0, "preco": 27.49, "doc": "FCL-LX626/006357", "data": "2026-05-22", "lote": "L036040B190", "val": "2026-09-15", "desc": "Pao Hamb. Cong. Bimbo 76x10 Cm +/- 55 Gr"}], "1576": [{"qt": 1.0, "preco": 44.09, "doc": "FCL-LS626/006924", "data": "2026-05-29", "lote": "326163", "val": "2026-06-12", "desc": "Ovos Industria L Uli Cx 15 Dz"}], "1582": [{"qt": 1.0, "preco": 40.99, "doc": "FCL-LS226/027951", "data": "2026-04-20", "lote": "326124", "val": "2026-05-04", "desc": "Ovos Pastelaria M Uli Cx 15 Dz"}], "15955": [{"qt": 3.0, "preco": 14.19, "doc": "FCL-LS226/011239", "data": "2026-01-16", "lote": "G1225306", "val": "2027-10-31", "desc": "Batata Allumete Cong.Metro Chef 4x2,5Kg"}, {"qt": 2.0, "preco": 14.19, "doc": "FCL-LS226/017123", "data": "2026-01-26", "lote": "L5334", "val": "2027-11-30", "desc": "Batata Allumete Cong.Metro Chef 4x2,5Kg"}, {"qt": 3.0, "preco": 14.19, "doc": "FCL-LX226/005597", "data": "2026-02-10", "lote": "L5334", "val": "2027-11-30", "desc": "Batata Allumete Cong.Metro Chef 4x2,5Kg"}, {"qt": 2.0, "preco": 14.19, "doc": "FCL-LX226/011940", "data": "2026-02-18", "lote": "L5334", "val": "2027-11-30", "desc": "Batata Allumete Cong.Metro Chef 4x2,5Kg"}, {"qt": 4.0, "preco": 14.19, "doc": "FCL-LX226/021616", "data": "2026-03-02", "lote": "L5334", "val": "2027-11-30", "desc": "Batata Allumete Cong.Metro Chef 4x2,5Kg"}, {"qt": 3.0, "preco": 14.19, "doc": "FCL-LX226/028293", "data": "2026-03-10", "lote": "L5334", "val": "2027-11-30", "desc": "Batata Allumete Cong.Metro Chef 4x2,5Kg"}, {"qt": 3.0, "preco": 14.19, "doc": "FCL-LX226/035631", "data": "2026-03-20", "lote": "L6005", "val": "2028-01-05", "desc": "Batata Allumete Cong.Metro Chef 4x2,5Kg"}, {"qt": 4.0, "preco": 14.19, "doc": "FCL-LX226/043361", "data": "2026-04-06", "lote": "L6006", "val": "2028-01-06", "desc": "Batata Allumete Cong.Metro Chef 4x2,5Kg"}, {"qt": 2.0, "preco": 14.19, "doc": "FCL-LX226/050014", "data": "2026-04-20", "lote": "L6006", "val": "2028-01-06", "desc": "Batata Allumete Cong.Metro Chef 4x2,5Kg"}, {"qt": 2.0, "preco": 14.19, "doc": "FCL-LX326/019753", "data": "2026-04-23", "lote": "L6006", "val": "2028-01-06", "desc": "Batata Allumete Cong.Metro Chef 4x2,5Kg"}, {"qt": 3.0, "preco": 14.19, "doc": "FCL-LX226/056906", "data": "2026-05-04", "lote": "L6006", "val": "2028-01-06", "desc": "Batata Allumete Cong.Metro Chef 4x2,5Kg"}, {"qt": 4.0, "preco": 14.19, "doc": "FCL-LX626/003192", "data": "2026-05-07", "lote": "L6006", "val": "2028-01-06", "desc": "Batata Allumete Cong.Metro Chef 4x2,5Kg"}, {"qt": 4.0, "preco": 14.19, "doc": "FCL-LX626/006357", "data": "2026-05-22", "lote": "L6082", "val": "2028-03-23", "desc": "Batata Allumete Cong.Metro Chef 4x2,5Kg"}, {"qt": 2.0, "preco": 14.19, "doc": "FCL-LX626/007325", "data": "2026-05-29", "lote": "L6082", "val": "2028-03-23", "desc": "Batata Allumete Cong.Metro Chef 4x2,5Kg"}, {"qt": 4.0, "preco": 14.19, "doc": "FCL-LX326/027773", "data": "2026-06-12", "lote": "L6109", "val": "2028-04-19", "desc": "Batata Allumete Cong.Metro Chef 4x2,5Kg"}], "15988": [{"qt": 4.0, "preco": 5.99, "doc": "FCL-LS225/118973", "data": "2025-10-20", "lote": "025272", "val": "2025-11-28", "desc": "Qj.Fresco Barra Uli 1 Kg"}, {"qt": 3.0, "preco": 5.99, "doc": "FCL-LS325/039527", "data": "2025-10-30", "lote": "025272", "val": "2025-11-28", "desc": "Qj.Fresco Barra Uli 1 Kg"}, {"qt": 3.0, "preco": 5.49, "doc": "FCL-LX325/002595", "data": "2025-11-06", "lote": "025283", "val": "2025-12-09", "desc": "Qj.Fresco Barra Uli 1 Kg"}, {"qt": 4.0, "preco": 5.49, "doc": "FCL-LS225/143122", "data": "2025-11-17", "lote": "025301", "val": "2025-12-27", "desc": "Qj.Fresco Barra Uli 1 Kg"}, {"qt": 2.0, "preco": 5.49, "doc": "FCL-LS225/148949", "data": "2025-11-24", "lote": "025301", "val": "2025-12-27", "desc": "Qj.Fresco Barra Uli 1 Kg"}, {"qt": 2.0, "preco": 5.99, "doc": "FCL-LS225/155040", "data": "2025-12-01", "lote": "025315", "val": "2026-01-10", "desc": "Qj.Fresco Barra Uli 1 Kg"}, {"qt": 3.0, "preco": 5.49, "doc": "FCL-LS226/004802", "data": "2026-01-07", "lote": "025356", "val": "2026-02-20", "desc": "Qj.Fresco Barra Uli 1 Kg"}, {"qt": 1.0, "preco": 5.49, "doc": "FCL-LS226/019351", "data": "2026-01-28", "lote": "026005", "val": "2026-03-06", "desc": "Qj.Fresco Barra Uli 1 Kg"}, {"qt": 3.0, "preco": 4.89, "doc": "FCL-LX226/011940", "data": "2026-02-18", "lote": "026034", "val": "2026-04-04", "desc": "Qj.Fresco Barra Uli 1 Kg"}, {"qt": 3.0, "preco": 5.89, "doc": "FCL-LX226/021616", "data": "2026-03-02", "lote": "026047", "val": "2026-04-17", "desc": "Qj.Fresco Barra Uli 1 Kg"}, {"qt": 2.0, "preco": 5.89, "doc": "FCL-LX226/028293", "data": "2026-03-10", "lote": "026047", "val": "2026-04-17", "desc": "Qj.Fresco Barra Uli 1 Kg"}, {"qt": 3.0, "preco": 5.89, "doc": "FCL-LX226/035631", "data": "2026-03-20", "lote": "026062", "val": "2026-06-01", "desc": "Qj.Fresco Barra Uli 1 Kg"}, {"qt": 2.0, "preco": 5.89, "doc": "FCL-LX226/043361", "data": "2026-04-06", "lote": "026076", "val": "2026-06-15", "desc": "Qj.Fresco Barra Uli 1 Kg"}, {"qt": 3.0, "preco": 5.89, "doc": "FCL-LX226/050014", "data": "2026-04-20", "lote": "026076", "val": "2026-06-15", "desc": "Qj.Fresco Barra Uli 1 Kg"}, {"qt": 4.0, "preco": 5.89, "doc": "FCL-LX326/019753", "data": "2026-04-23", "lote": "026076", "val": "2026-06-15", "desc": "Qj.Fresco Barra Uli 1 Kg"}, {"qt": 2.0, "preco": 5.89, "doc": "FCL-LS226/032356", "data": "2026-05-04", "lote": "026110", "val": "2026-07-19", "desc": "Qj.Fresco Barra Uli 1 Kg"}, {"qt": 2.0, "preco": 5.89, "doc": "FCL-LS626/002554", "data": "2026-05-07", "lote": "026110", "val": "2026-07-19", "desc": "Qj.Fresco Barra Uli 1 Kg"}], "16518": [{"qt": 1.0, "preco": 19.99, "doc": "FCL-LX226/028293", "data": "2026-03-10", "lote": "L26024500005", "val": "2027-08-31", "desc": "Oleo Alimentar Alto Rendimento Uli 10 L"}, {"qt": 1.0, "preco": 19.99, "doc": "FCL-LS026/003494", "data": "2026-04-23", "lote": "L26033400015", "val": "2027-09-16", "desc": "Oleo Alimentar Alto Rendimento Uli 10 L"}], "16659": [{"qt": 1.0, "preco": 34.99, "doc": "FCL-LS225/118973", "data": "2025-10-20", "lote": "236", "val": "2025-11-05", "desc": "Ovos M Uniovo Cx 15 Dz"}, {"qt": 1.0, "preco": 34.99, "doc": "FCL-LS225/125051", "data": "2025-10-27", "lote": "240", "val": "2025-11-10", "desc": "Ovos M Uniovo Cx 15 Dz"}, {"qt": 1.0, "preco": 34.99, "doc": "FCL-LS325/039527", "data": "2025-10-30", "lote": "248", "val": "2025-11-19", "desc": "Ovos M Uniovo Cx 15 Dz"}, {"qt": 1.0, "preco": 40.19, "doc": "FCL-LS225/134992", "data": "2025-11-06", "lote": "253", "val": "2025-11-25", "desc": "Ovos M Uniovo Cx 15 Dz"}, {"qt": 1.0, "preco": 40.19, "doc": "FCL-LS225/143122", "data": "2025-11-17", "lote": "259", "val": "2025-12-02", "desc": "Ovos M Uniovo Cx 15 Dz"}, {"qt": 1.0, "preco": 40.19, "doc": "FCL-LS225/148949", "data": "2025-11-24", "lote": "263", "val": "2025-12-06", "desc": "Ovos M Uniovo Cx 15 Dz"}], "5082": [{"qt": 2.0, "preco": 21.95, "doc": "FCL-LS225/104676", "data": "2025-10-03", "lote": "5182", "val": "2027-07-01", "desc": "Batata Cong.Allumete 7/7 Lutosa 4x2.5 Kg"}, {"qt": 2.0, "preco": 20.49, "doc": "FCL-LS225/108953", "data": "2025-10-08", "lote": "5253", "val": "2027-09-10", "desc": "Batata Cong.Allumete 7/7 Lutosa 4x2.5 Kg"}, {"qt": 2.0, "preco": 20.49, "doc": "FCL-LS225/115082", "data": "2025-10-15", "lote": "5253", "val": "2027-09-10", "desc": "Batata Cong.Allumete 7/7 Lutosa 4x2.5 Kg"}, {"qt": 2.0, "preco": 20.49, "doc": "FCL-LS225/118973", "data": "2025-10-20", "lote": "5252", "val": "2027-09-09", "desc": "Batata Cong.Allumete 7/7 Lutosa 4x2.5 Kg"}, {"qt": 3.0, "preco": 20.49, "doc": "FCL-LS225/125051", "data": "2025-10-27", "lote": "5255", "val": "2027-09-12", "desc": "Batata Cong.Allumete 7/7 Lutosa 4x2.5 Kg"}, {"qt": 3.0, "preco": 20.49, "doc": "FCL-LS325/039527", "data": "2025-10-30", "lote": "5253", "val": "2027-09-10", "desc": "Batata Cong.Allumete 7/7 Lutosa 4x2.5 Kg"}, {"qt": 2.0, "preco": 20.49, "doc": "FCL-LS225/134992", "data": "2025-11-06", "lote": "5255", "val": "2027-09-12", "desc": "Batata Cong.Allumete 7/7 Lutosa 4x2.5 Kg"}, {"qt": 3.0, "preco": 20.49, "doc": "FCL-LS225/143122", "data": "2025-11-17", "lote": "5255", "val": "2027-09-12", "desc": "Batata Cong.Allumete 7/7 Lutosa 4x2.5 Kg"}, {"qt": 3.0, "preco": 20.49, "doc": "FCL-LS225/148949", "data": "2025-11-24", "lote": "5253", "val": "2027-09-10", "desc": "Batata Cong.Allumete 7/7 Lutosa 4x2.5 Kg"}, {"qt": 4.0, "preco": 21.95, "doc": "FCL-LS225/155040", "data": "2025-12-01", "lote": "5253", "val": "2027-09-10", "desc": "Batata Cong.Allumete 7/7 Lutosa 4x2.5 Kg"}, {"qt": 2.0, "preco": 21.69, "doc": "FCL-LS225/166849", "data": "2025-12-15", "lote": "5253", "val": "2027-09-10", "desc": "Batata Cong.Allumete 7/7 Lutosa 4x2.5 Kg"}, {"qt": 2.0, "preco": 20.49, "doc": "FCL-LS226/004802", "data": "2026-01-07", "lote": "5255", "val": "2027-09-12", "desc": "Batata Cong.Allumete 7/7 Lutosa 4x2.5 Kg"}], "60504": [{"qt": 1.0, "preco": 17.79, "doc": "FCL-LS225/108953", "data": "2025-10-08", "lote": "E2555", "val": "2027-03-13", "desc": "Salmao Fumado Fatiado Cong. 1 Kg"}, {"qt": 1.0, "preco": 17.79, "doc": "FCL-LS225/115082", "data": "2025-10-15", "lote": "E2555", "val": "2027-03-13", "desc": "Salmao Fumado Fatiado Cong. 1 Kg"}, {"qt": 1.0, "preco": 17.79, "doc": "FCL-LS325/039527", "data": "2025-10-30", "lote": "E2555", "val": "2027-03-13", "desc": "Salmao Fumado Fatiado Cong. 1 Kg"}, {"qt": 1.0, "preco": 17.79, "doc": "FCL-LS225/143122", "data": "2025-11-17", "lote": "E2555", "val": "2027-03-13", "desc": "Salmao Fumado Fatiado Cong. 1 Kg"}, {"qt": 1.0, "preco": 18.99, "doc": "FCL-LX226/011940", "data": "2026-02-18", "lote": "E2566", "val": "2027-03-14", "desc": "Salmao Fumado Fatiado Cong. 1 Kg"}, {"qt": 2.0, "preco": 18.95, "doc": "FCL-LX326/027773", "data": "2026-06-12", "lote": "F1215", "val": "2027-10-30", "desc": "Salmao Fumado Fatiado Cong. 1 Kg"}], "6503": [{"qt": 0.982, "preco": 21.0, "doc": "FCL-LS225/104676", "data": "2025-10-03", "lote": "U76921925", "val": "2026-10-28", "desc": "Salmao Fumado Cong.Fatia.Dinamarca Vacuo"}, {"qt": 1.066, "preco": 19.5, "doc": "FCL-LS225/134992", "data": "2025-11-06", "lote": "U76931925", "val": "2026-10-29", "desc": "Salmao Fumado Cong.Fatia.Dinamarca Vacuo"}], "65143": [{"qt": 6.471, "preco": 8.49, "doc": "FCL-LS225/108953", "data": "2025-10-08", "lote": "352613100434", "val": "2026-09-13", "desc": "Hamb.Bov.100g Cong.Uli Cx +/- 6 Kg 60 Un"}, {"qt": 6.471, "preco": 8.49, "doc": "FCL-LS325/039527", "data": "2025-10-30", "lote": "351413100434", "val": "2026-05-16", "desc": "Hamb.Bov.100g Cong.Uli Cx +/- 6 Kg 60 Un"}, {"qt": 6.351, "preco": 8.99, "doc": "FCL-LS225/148949", "data": "2025-11-24", "lote": "352471980701", "val": "2026-08-30", "desc": "Hamb.Bov.100g Cong.Uli Cx +/- 6 Kg 60 Un"}, {"qt": 6.091, "preco": 8.99, "doc": "FCL-LS226/017123", "data": "2026-01-26", "lote": "360215330010", "val": "2027-01-17", "desc": "Hamb.Bov.100g Cong.Uli Cx +/- 6 Kg 60 Un"}, {"qt": 6.111, "preco": 8.99, "doc": "FCL-LX226/011940", "data": "2026-02-18", "lote": "360410910434", "val": "2027-02-05", "desc": "Hamb.Bov.100g Cong.Uli Cx +/- 6 Kg 60 Un"}, {"qt": 6.151, "preco": 9.09, "doc": "FCL-LX226/043361", "data": "2026-04-06", "lote": "360152920434", "val": "2027-01-10", "desc": "Hamb.Bov.100g Cong.Uli Cx +/- 6 Kg 60 Un"}, {"qt": 6.051, "preco": 9.09, "doc": "FCL-LX226/056906", "data": "2026-05-04", "lote": "361130910434", "val": "2027-04-18", "desc": "Hamb.Bov.100g Cong.Uli Cx +/- 6 Kg 60 Un"}, {"qt": 6.071, "preco": 9.09, "doc": "FCL-LX326/027773", "data": "2026-06-12", "lote": "360715330013", "val": "2027-03-07", "desc": "Hamb.Bov.100g Cong.Uli Cx +/- 6 Kg 60 Un"}], "65202": [{"qt": 12.036, "preco": 7.09, "doc": "FCL-LX626/006357", "data": "2026-05-22", "lote": "360625330013", "val": "2027-02-26", "desc": "Hamb.Bov FS 80g Cong.Uli Cx +/-6 Kg"}], "73050": [{"qt": 2.49, "preco": 10.46, "doc": "FCL-LS225/104676", "data": "2025-10-03", "lote": "352753100434", "val": "2025-10-10", "desc": "Hamb Bovino Fresco Uli Bandeja"}], "7386": [{"qt": 1.0, "preco": 46.99, "doc": "FCL-LS225/125051", "data": "2025-10-27", "lote": "L5062", "val": "2026-03-02", "desc": "Hamb.Bovino Cong.Dawn Chef 40x113 Gr"}, {"qt": 1.0, "preco": 49.99, "doc": "FCL-LS226/004802", "data": "2026-01-07", "lote": "L5143", "val": "2026-05-22", "desc": "Hamb.Bovino Cong.Dawn Chef 40x113 Gr"}], "7771": [{"qt": 2.0, "preco": 6.99, "doc": "FCL-LS225/118973", "data": "2025-10-20", "lote": "25433287", "val": "2026-02-11", "desc": "Presunto Fatiado Uli 500 Gr"}, {"qt": 3.0, "preco": 6.99, "doc": "FCL-LS226/017123", "data": "2026-01-26", "lote": "26008010", "val": "2026-05-10", "desc": "Presunto Fatiado Uli 500 Gr"}], "8315": [{"qt": 1.0, "preco": 33.0, "doc": "FCL-LS225/104676", "data": "2025-10-03", "lote": "3625228", "val": "2026-08-16", "desc": "Tortillas Trigo Mexic.25Cm Cong.144x63Gr"}, {"qt": 1.0, "preco": 33.0, "doc": "FCL-LS225/115082", "data": "2025-10-15", "lote": "3625228", "val": "2026-08-16", "desc": "Tortillas Trigo Mexic.25Cm Cong.144x63Gr"}, {"qt": 1.0, "preco": 32.99, "doc": "FCL-LS225/134992", "data": "2025-11-06", "lote": "3625228", "val": "2026-08-16", "desc": "Tortillas Trigo Mexic.25Cm Cong.144x63Gr"}, {"qt": 1.0, "preco": 32.99, "doc": "FCL-LS225/148949", "data": "2025-11-24", "lote": "3625228", "val": "2026-08-16", "desc": "Tortillas Trigo Mexic.25Cm Cong.144x63Gr"}, {"qt": 1.0, "preco": 32.99, "doc": "FCL-LS226/004802", "data": "2026-01-07", "lote": "3625228", "val": "2026-08-16", "desc": "Tortillas Trigo Mexic.25Cm Cong.144x63Gr"}, {"qt": 1.0, "preco": 32.99, "doc": "FCL-LX226/005597", "data": "2026-02-10", "lote": "3625228", "val": "2026-08-16", "desc": "Tortillas Trigo Mexic.25Cm Cong.144x63Gr"}, {"qt": 1.0, "preco": 32.99, "doc": "FCL-LX226/021616", "data": "2026-03-02", "lote": "3625303", "val": "2026-10-30", "desc": "Tortillas Trigo Mexic.25Cm Cong.144x63Gr"}, {"qt": 1.0, "preco": 32.99, "doc": "FCL-LX226/035631", "data": "2026-03-20", "lote": "3625303", "val": "2026-10-30", "desc": "Tortillas Trigo Mexic.25Cm Cong.144x63Gr"}, {"qt": 1.0, "preco": 32.99, "doc": "FCL-LX326/019753", "data": "2026-04-23", "lote": "4726048", "val": "2027-02-17", "desc": "Tortillas Trigo Mexic.25Cm Cong.144x63Gr"}, {"qt": 1.0, "preco": 32.99, "doc": "FCL-LX626/003192", "data": "2026-05-07", "lote": "4726048", "val": "2027-02-17", "desc": "Tortillas Trigo Mexic.25Cm Cong.144x63Gr"}, {"qt": 2.0, "preco": 32.99, "doc": "FCL-LX626/007325", "data": "2026-05-29", "lote": "4726048", "val": "2027-02-17", "desc": "Tortillas Trigo Mexic.25Cm Cong.144x63Gr"}, {"qt": 2.0, "preco": 29.69, "doc": "FCL-LX326/027773", "data": "2026-06-12", "lote": "4726048", "val": "2027-02-17", "desc": "Tortillas Trigo Mexic.25Cm Cong.144x63Gr"}], "8986": [{"qt": 1.0, "preco": 19.79, "doc": "FCL-LS325/039527", "data": "2025-10-30", "lote": "5252", "val": "2028-09-09", "desc": "Salsichas Fumadas Hot Dog Lt 2x35 Un"}]}