{"15268": [{"qt": 8.0, "preco": 35.2, "doc": "FCL-LS225/123577", "data": "2025-10-24", "lote": "1272S", "val": "2026-09-29", "desc": "Empada Galinha Med.Cong.+/- 80Gr Cx 50Un"}], "15274": [{"qt": 8.0, "preco": 35.19, "doc": "FCL-LS225/123577", "data": "2025-10-24", "lote": "4282S", "val": "2026-10-09", "desc": "Empada Espinafre Med.Cong.+/-80G Cx 50Un"}], "15276": [{"qt": 4.0, "preco": 40.69, "doc": "FCL-LS225/162574", "data": "2025-12-10", "lote": "4254S", "val": "2026-09-11", "desc": "Empada Pato Med.Cong.+/- 80 Gr Cx 50 Un"}], "15357": [{"qt": 2.0, "preco": 18.95, "doc": "FCL-LS225/109564", "data": "2025-10-09", "lote": "1001059989", "val": "2026-10-26", "desc": "Mini Cereais Artis Cong.120x46 Gr"}], "15487": [{"qt": 1.0, "preco": 8.65, "doc": "FCL-LS225/156661", "data": "2025-12-03", "lote": "L1183BJ", "val": "2027-10-31", "desc": "Sardinha Oleo Nau Catrineta 10x120 Gr"}, {"qt": 1.0, "preco": 8.65, "doc": "FCL-LS226/020328", "data": "2026-01-30", "lote": "L1183BJ", "val": "2027-10-31", "desc": "Sardinha Oleo Nau Catrineta 10x120 Gr"}], "15488": [{"qt": 1.0, "preco": 8.65, "doc": "FCL-LS225/156661", "data": "2025-12-03", "lote": "L2549CA", "val": "2029-03-31", "desc": "Sardinha Tomate Nau Catrineta 10x120 Gr"}, {"qt": 2.0, "preco": 8.65, "doc": "FCL-LS226/020328", "data": "2026-01-30", "lote": "L2549CA", "val": "2029-03-31", "desc": "Sardinha Tomate Nau Catrineta 10x120 Gr"}], "15490": [{"qt": 1.0, "preco": 8.65, "doc": "FCL-LS225/156661", "data": "2025-12-03", "lote": "L2188DY", "val": "2028-03-31", "desc": "Sardinha Tom.Pic Nau Catrineta 10x120 Gr"}, {"qt": 2.0, "preco": 8.65, "doc": "FCL-LS226/020328", "data": "2026-01-30", "lote": "L2188DY", "val": "2028-03-31", "desc": "Sardinha Tom.Pic Nau Catrineta 10x120 Gr"}], "15499": [{"qt": 1.0, "preco": 9.79, "doc": "FCL-LS225/103886", "data": "2025-10-03", "lote": "021125", "val": "2025-11-02", "desc": "Iog. Liquido Morango Mimosa 24x151 Ml"}], "15514": [{"qt": 1.0, "preco": 9.79, "doc": "FCL-LS225/103886", "data": "2025-10-03", "lote": "261025", "val": "2025-10-26", "desc": "Iog.Liquido F.Tropicais Mimosa 24x151 Ml"}], "15686": [{"qt": 2.0, "preco": 23.99, "doc": "FCL-LX026/002598", "data": "2026-03-24", "lote": "30225006", "val": "2027-10-30", "desc": "Mel Flores 6x1 Kg"}], "15706": [{"qt": 4.0, "preco": 10.89, "doc": "FCL-LS225/156661", "data": "2025-12-03", "lote": "1U126725", "val": "2026-08-20", "desc": "Bebida Vegetal Soja Shoyce 24x200 ml"}], "15779": [{"qt": 4.0, "preco": 22.49, "doc": "FCL-LS225/165419", "data": "2025-12-12", "lote": "75125304", "val": "2026-10-31", "desc": "Foccacia Mediterr.Cong.Lanterna 4x800 Gr"}, {"qt": 2.0, "preco": 22.49, "doc": "FCL-LX226/025494", "data": "2026-03-06", "lote": "75125304", "val": "2026-10-31", "desc": "Foccacia Mediterr.Cong.Lanterna 4x800 Gr"}], "1579": [{"qt": 2.0, "preco": 13.19, "doc": "FCL-LS225/103886", "data": "2025-10-03", "lote": "23291", "val": "2025-10-18", "desc": "Ovos Industria M Uli Cx 5 Dz"}], "15855": [{"qt": 1.0, "preco": 11.99, "doc": "FCL-LS225/156661", "data": "2025-12-03", "lote": "1I108925", "val": "2026-03-30", "desc": "Bebida Vegetal Soja.Bauni Shoyce24x200ml"}], "15859": [{"qt": 2.0, "preco": 17.09, "doc": "FCL-LS225/156661", "data": "2025-12-03", "lote": "1B114025", "val": "2026-05-20", "desc": "Bebida Vegetal Choco Shoyce 24x200 ml"}], "15936": [{"qt": 2.0, "preco": 31.95, "doc": "FCL-LS225/103886", "data": "2025-10-03", "lote": "0753825", "val": "2027-03-21", "desc": "Empadas Frango Peq.Cong.Uli Cx100 Un"}, {"qt": 2.0, "preco": 31.95, "doc": "FCL-LS225/112089", "data": "2025-10-11", "lote": "0734025", "val": "2027-04-02", "desc": "Empadas Frango Peq.Cong.Uli Cx100 Un"}, {"qt": 2.0, "preco": 30.95, "doc": "FCL-LS225/162574", "data": "2025-12-10", "lote": "0714825", "val": "2027-05-26", "desc": "Empadas Frango Peq.Cong.Uli Cx100 Un"}, {"qt": 5.0, "preco": 31.49, "doc": "FCL-LX226/060082", "data": "2026-05-09", "lote": "0711526", "val": "2027-10-06", "desc": "Empadas Frango Peq.Cong.Uli Cx100 Un"}], "15939": [{"qt": 2.0, "preco": 12.19, "doc": "FCL-LS225/103886", "data": "2025-10-03", "lote": "L2231250301", "val": "2026-11-30", "desc": "Maionese Uli Balde 4,5 kg"}], "15983": [{"qt": 2.0, "preco": 29.79, "doc": "FCL-LX226/060082", "data": "2026-05-09", "lote": "21125", "val": "2027-07-17", "desc": "Macarons 6 Sabores Cong. TDP Cx 72Un"}], "15988": [{"qt": 6.0, "preco": 5.89, "doc": "FCL-LX226/051234", "data": "2026-04-22", "lote": "026076", "val": "2026-06-15", "desc": "Qj.Fresco Barra Uli 1 Kg"}], "15991": [{"qt": 5.0, "preco": 7.89, "doc": "FCL-LX026/002598", "data": "2026-03-24", "lote": "030326", "val": "2026-06-01", "desc": "Qj.Edam Light Fatiado Uli 1 kg"}, {"qt": 10.0, "preco": 7.89, "doc": "FCL-LX026/003705", "data": "2026-03-26", "lote": "170326", "val": "2026-06-15", "desc": "Qj.Edam Light Fatiado Uli 1 kg"}], "15994": [{"qt": 15.0, "preco": 7.19, "doc": "FCL-LS326/014517", "data": "2026-05-18", "lote": "280426", "val": "2026-07-27", "desc": "Qj.Flamengo Fatiado Uli 1 kg"}], "16013": [{"qt": 20.0, "preco": 4.49, "doc": "FCL-LX026/003705", "data": "2026-03-26", "lote": "11626", "val": "2026-05-12", "desc": "Bacon Fatiado Uli 500 Gr"}], "16046": [{"qt": 1.0, "preco": 19.9, "doc": "FCL-LS225/103886", "data": "2025-10-03", "lote": "1000038986", "val": "2027-06-11", "desc": "Grelos Porcoes Cong. 10x1 Kg"}], "16049": [{"qt": 1.0, "preco": 39.35, "doc": "FCL-LS225/156661", "data": "2025-12-03", "lote": "L61057", "val": "2026-04-03", "desc": "Cebola Frita Desidratada 5x1 Kg"}], "16099": [{"qt": 6.0, "preco": 12.39, "doc": "FCL-LX226/057955", "data": "2026-05-06", "lote": "VN602II101", "val": "2027-06-20", "desc": "Camarao Torpedo Panado Cong. 1 Kg"}, {"qt": 10.0, "preco": 12.39, "doc": "FCL-LX226/060082", "data": "2026-05-09", "lote": "VN602II101", "val": "2027-06-20", "desc": "Camarao Torpedo Panado Cong. 1 Kg"}], "16140": [{"qt": 2.0, "preco": 12.99, "doc": "FCL-LX226/051234", "data": "2026-04-22", "lote": "VQRI", "val": "2026-05-28", "desc": "Iogurte Grego Cremoso 3,5 kg"}], "16143": [{"qt": 1.0, "preco": 9.99, "doc": "FCL-LS225/103886", "data": "2025-10-03", "lote": "L5119CL099", "val": "2025-12-25", "desc": "Maionese Vegan Hellmann’s Balde 2 kg"}], "16178": [{"qt": 2.0, "preco": 8.95, "doc": "FCL-LX226/051234", "data": "2026-04-22", "lote": "L20260401", "val": "2027-09-30", "desc": "Gelado Cuba Baunilha Cong.MetroChef 4,5l"}], "16183": [{"qt": 1.0, "preco": 8.95, "doc": "FCL-LX026/002598", "data": "2026-03-24", "lote": "L20260309", "val": "2027-08-31", "desc": "Gelado Cuba Limao Cong. MetroChef 4,5 l"}], "16320": [{"qt": 2.0, "preco": 10.14, "doc": "FCL-LX026/004901", "data": "2026-03-28", "lote": "L5252OON51", "val": "2026-06-30", "desc": "Molho Sweet Chili Knorr 1 l"}], "16355": [{"qt": 3.0, "preco": 14.45, "doc": "FCL-LS225/109564", "data": "2025-10-09", "lote": "15250827", "val": "2026-08-27", "desc": "Pao Rustico p/Tosta Fat. XL Cong.2x3 Kg"}], "16408": [{"qt": 6.0, "preco": 20.19, "doc": "FCL-LX026/002598", "data": "2026-03-24", "lote": "L01826", "val": "2026-07-19", "desc": "Nata Culinaria UHT METRO Chef 6x1 l"}], "16484": [{"qt": 2.0, "preco": 37.95, "doc": "FCL-LS225/103886", "data": "2025-10-03", "lote": "C0125374", "val": "2027-03-11", "desc": "Bolinhas Alheira Forno Cong.Uli 160x25 g"}, {"qt": 1.0, "preco": 38.95, "doc": "FCL-LX026/006314", "data": "2026-04-02", "lote": "C0126103", "val": "2027-09-04", "desc": "Bolinhas Alheira Forno Cong.Uli 160x25 g"}, {"qt": 2.0, "preco": 34.99, "doc": "FCL-LX326/021037", "data": "2026-05-13", "lote": "C0126142", "val": "2027-09-30", "desc": "Bolinhas Alheira Forno Cong.Uli 160x25 g"}], "16518": [{"qt": 3.0, "preco": 19.99, "doc": "FCL-LS226/029626", "data": "2026-04-24", "lote": "L26033400015", "val": "2027-09-16", "desc": "Oleo Alimentar Alto Rendimento Uli 10 L"}], "16519": [{"qt": 4.0, "preco": 23.99, "doc": "FCL-LS226/020328", "data": "2026-01-30", "lote": "L25122302294", "val": "2027-05-31", "desc": "Azeite Virgem Extra Uli 5L"}, {"qt": 2.0, "preco": 24.19, "doc": "FCL-LX026/002598", "data": "2026-03-24", "lote": "L25135401691", "val": "2027-05-31", "desc": "Azeite Virgem Extra Uli 5L"}], "16534": [{"qt": 4.0, "preco": 14.0, "doc": "FCL-LX026/006314", "data": "2026-04-02", "lote": "75125300", "val": "2026-10-31", "desc": "Focaccia Tradi. Lanterna Cong. Vm 4x600g"}, {"qt": 9.0, "preco": 14.0, "doc": "FCL-LX226/062698", "data": "2026-05-19", "lote": "75125300", "val": "2026-10-31", "desc": "Focaccia Tradi. Lanterna Cong. Vm 4x600g"}], "16563": [{"qt": 2.0, "preco": 25.95, "doc": "FCL-LS225/131753", "data": "2025-11-04", "lote": "75255129", "val": "2026-05-31", "desc": "Pao Panini Pre-cortado Cong.Vm 54x80g"}, {"qt": 1.0, "preco": 25.95, "doc": "FCL-LS225/141341", "data": "2025-11-14", "lote": "75255239", "val": "2026-08-31", "desc": "Pao Panini Pre-cortado Cong.Vm 54x80g"}, {"qt": 1.0, "preco": 25.95, "doc": "FCL-LS225/149615", "data": "2025-11-25", "lote": "75255239", "val": "2026-08-31", "desc": "Pao Panini Pre-cortado Cong.Vm 54x80g"}, {"qt": 1.0, "preco": 25.95, "doc": "FCL-LS225/162574", "data": "2025-12-10", "lote": "75255239", "val": "2026-08-31", "desc": "Pao Panini Pre-cortado Cong.Vm 54x80g"}, {"qt": 1.0, "preco": 25.95, "doc": "FCL-LS225/168965", "data": "2025-12-17", "lote": "75255239", "val": "2026-08-31", "desc": "Pao Panini Pre-cortado Cong.Vm 54x80g"}, {"qt": 1.0, "preco": 25.95, "doc": "FCL-LS226/008057", "data": "2026-01-13", "lote": "75255239", "val": "2026-08-31", "desc": "Pao Panini Pre-cortado Cong.Vm 54x80g"}, {"qt": 2.0, "preco": 25.95, "doc": "FCL-LX226/025494", "data": "2026-03-06", "lote": "75255239", "val": "2026-08-31", "desc": "Pao Panini Pre-cortado Cong.Vm 54x80g"}, {"qt": 2.0, "preco": 25.95, "doc": "FCL-LX026/004901", "data": "2026-03-28", "lote": "75255239", "val": "2026-08-31", "desc": "Pao Panini Pre-cortado Cong.Vm 54x80g"}, {"qt": 1.0, "preco": 25.95, "doc": "FCL-LX226/052687", "data": "2026-04-24", "lote": "75256071", "val": "2027-03-31", "desc": "Pao Panini Pre-cortado Cong.Vm 54x80g"}, {"qt": 2.0, "preco": 25.95, "doc": "FCL-LX226/060082", "data": "2026-05-09", "lote": "75256071", "val": "2027-03-31", "desc": "Pao Panini Pre-cortado Cong.Vm 54x80g"}, {"qt": 2.0, "preco": 25.95, "doc": "FCL-LX026/021428", "data": "2026-06-02", "lote": "75256071", "val": "2027-03-31", "desc": "Pao Panini Pre-cortado Cong.Vm 54x80g"}], "16682": [{"qt": 4.0, "preco": 10.35, "doc": "FCL-LS225/156661", "data": "2025-12-03", "lote": "L5341", "val": "2027-10-31", "desc": "Arroz Basmati Metro Chef 5 kg"}, {"qt": 1.0, "preco": 9.95, "doc": "FCL-LS226/029626", "data": "2026-04-24", "lote": "L6116", "val": "2028-04-30", "desc": "Arroz Basmati Metro Chef 5 kg"}], "16788": [{"qt": 2.0, "preco": 19.99, "doc": "FCL-LX226/025494", "data": "2026-03-06", "lote": "P02954", "val": "2026-04-06", "desc": "Ovo Cozido METRO Chef Balde 60 Un"}], "16802": [{"qt": 5.0, "preco": 28.99, "doc": "FCL-LS225/141341", "data": "2025-11-14", "lote": "L35385", "val": "2026-06-28", "desc": "Granola Frutos Secos Nacional 7x300 g"}, {"qt": 3.0, "preco": 28.99, "doc": "FCL-LS226/032899", "data": "2026-05-05", "lote": "L35136", "val": "2026-12-28", "desc": "Granola Frutos Secos Nacional 7x300 g"}, {"qt": 3.0, "preco": 28.99, "doc": "FCL-LS026/007899", "data": "2026-05-26", "lote": "L32186", "val": "2027-01-28", "desc": "Granola Frutos Secos Nacional 7x300 g"}, {"qt": 10.0, "preco": 28.99, "doc": "FCL-LS026/007899", "data": "2026-05-26", "lote": "L32186", "val": "2027-01-28", "desc": "Granola Frutos Secos Nacional 7x300 g"}, {"qt": 3.0, "preco": 28.99, "doc": "FCL-LS226/039245", "data": "2026-05-27", "lote": "L32186", "val": "2027-01-28", "desc": "Granola Frutos Secos Nacional 7x300 g"}, {"qt": -3.0, "preco": 28.99, "doc": "NCC-LS026/003970", "data": "2026-06-02", "lote": null, "val": null, "desc": "Granola Frutos Secos Nacional 7x300 g"}, {"qt": -10.0, "preco": 28.99, "doc": "NCC-LS026/003970", "data": "2026-06-02", "lote": null, "val": null, "desc": "Granola Frutos Secos Nacional 7x300 g"}], "16803": [{"qt": 5.0, "preco": 28.99, "doc": "FCL-LS225/141341", "data": "2025-11-14", "lote": "L33345", "val": "2026-05-28", "desc": "Granola Choc. Salgado Nacional 7x300 g"}, {"qt": 2.0, "preco": 28.99, "doc": "FCL-LS226/028715", "data": "2026-04-22", "lote": "L31076", "val": "2026-11-28", "desc": "Granola Choc. Salgado Nacional 7x300 g"}, {"qt": 2.0, "preco": 28.99, "doc": "FCL-LS226/032899", "data": "2026-05-05", "lote": "L36156", "val": "2027-01-20", "desc": "Granola Choc. Salgado Nacional 7x300 g"}, {"qt": 3.0, "preco": 28.99, "doc": "FCL-LS026/007899", "data": "2026-05-26", "lote": "L36196", "val": "2027-02-28", "desc": "Granola Choc. Salgado Nacional 7x300 g"}, {"qt": 10.0, "preco": 28.99, "doc": "FCL-LS026/007899", "data": "2026-05-26", "lote": "L36196", "val": "2027-02-28", "desc": "Granola Choc. Salgado Nacional 7x300 g"}, {"qt": 3.0, "preco": 28.99, "doc": "FCL-LS226/039245", "data": "2026-05-27", "lote": "L36196", "val": "2027-02-28", "desc": "Granola Choc. Salgado Nacional 7x300 g"}, {"qt": -3.0, "preco": 28.99, "doc": "NCC-LS026/003970", "data": "2026-06-02", "lote": null, "val": null, "desc": "Granola Choc. Salgado Nacional 7x300 g"}, {"qt": -10.0, "preco": 28.99, "doc": "NCC-LS026/003970", "data": "2026-06-02", "lote": null, "val": null, "desc": "Granola Choc. Salgado Nacional 7x300 g"}], "17042": [{"qt": 1.0, "preco": 22.49, "doc": "FCL-LS226/033262", "data": "2026-05-06", "lote": "025206001", "val": "2028-07-24", "desc": "Pepinos Extra Uli Frasco 6x720 g"}], "17152": [{"qt": 2.0, "preco": 16.79, "doc": "FCL-LS326/013584", "data": "2026-05-13", "lote": "40205809", "val": "2026-06-25", "desc": "Queijo Ricotta Fresco 2x1,5 kg"}], "1752": [{"qt": 1.0, "preco": 27.99, "doc": "FCL-LS225/165419", "data": "2025-12-12", "lote": "0909250099", "val": "2026-12-03", "desc": "Mini Panquecas Americanas Cong.100x25 Gr"}], "1890": [{"qt": 5.0, "preco": 20.59, "doc": "FCL-LS225/109564", "data": "2025-10-09", "lote": "5248B", "val": "2026-01-03", "desc": "Bolo Mel/Noz Cong. Cx +/- 1,8 Kg"}], "1920": [{"qt": 1.0, "preco": 5.59, "doc": "FCL-LS225/103886", "data": "2025-10-03", "lote": "221025", "val": "2025-10-22", "desc": "Iog.Natural Mimosa 24x120 Gr"}], "1977": [{"qt": 1.0, "preco": 26.65, "doc": "FCL-LS225/103886", "data": "2025-10-03", "lote": "223925", "val": "2026-09-28", "desc": "Quinoa Preta Uli Sc 5 Kg"}], "2000": [{"qt": 2.0, "preco": 8.29, "doc": "FCL-LX226/018398", "data": "2026-02-26", "lote": "0252610010011", "val": "2029-10-20", "desc": "Piri-Piri Po Uli Pet 810 Gr"}], "2036": [{"qt": 1.0, "preco": 70.99, "doc": "FCL-LX026/002598", "data": "2026-03-24", "lote": "L0566", "val": "2028-01-19", "desc": "Filete Robalo C/P Cong.120/140gr Cx 5 Kg"}], "2143": [{"qt": 1.0, "preco": 64.79, "doc": "FCL-LX026/002598", "data": "2026-03-24", "lote": "L0416", "val": "2027-12-18", "desc": "Filete Dourada C/P Cong.100/150gr Cx 5Kg"}, {"qt": 2.0, "preco": 64.79, "doc": "FCL-LX226/058925", "data": "2026-05-07", "lote": "L0976", "val": "2028-02-03", "desc": "Filete Dourada C/P Cong.100/150gr Cx 5Kg"}], "3184": [{"qt": 4.0, "preco": 10.35, "doc": "FCL-LS225/103886", "data": "2025-10-03", "lote": "L25426", "val": "2027-03-30", "desc": "Oleo Santa Filomena 5 Lt"}], "3250": [{"qt": 4.0, "preco": 20.99, "doc": "FCL-LX026/004901", "data": "2026-03-28", "lote": "L26026900103", "val": "2027-09-30", "desc": "Azeite Tradicional Uli Bl 5 Lt"}, {"qt": 2.0, "preco": 20.99, "doc": "FCL-LS226/028715", "data": "2026-04-22", "lote": "L26030400581", "val": "2027-09-30", "desc": "Azeite Tradicional Uli Bl 5 Lt"}, {"qt": 3.0, "preco": 20.99, "doc": "FCL-LS226/029626", "data": "2026-04-24", "lote": "L26028000581", "val": "2027-09-30", "desc": "Azeite Tradicional Uli Bl 5 Lt"}], "3437": [{"qt": 3.0, "preco": 12.55, "doc": "FCL-LS225/103886", "data": "2025-10-03", "lote": "052725", "val": "2026-03-28", "desc": "Caju Frito S/Sal Uli Saco 1 Kg"}], "3447": [{"qt": 2.0, "preco": 8.55, "doc": "FCL-LS225/103886", "data": "2025-10-03", "lote": "223025", "val": "2026-05-28", "desc": "Ameixa Seca S/Caroco Uli Covete 1 Kg"}], "3517": [{"qt": 1.0, "preco": 9.95, "doc": "FCL-LX226/015943", "data": "2026-02-24", "lote": "0251040030001", "val": "2028-04-30", "desc": "Mistura Garam Massala Uli Pet 910 Gr"}], "3522": [{"qt": 1.0, "preco": 6.99, "doc": "FCL-LX226/015943", "data": "2026-02-24", "lote": "0251480020010", "val": "2028-05-30", "desc": "Especiarias Ras El Hanout Uli Pet 910 Gr"}], "3551": [{"qt": 2.0, "preco": 3.25, "doc": "FCL-LX226/018398", "data": "2026-02-26", "lote": "9252330010011", "val": "2030-06-20", "desc": "Ervas Provencais Uli Pet 410 G"}], "3558": [{"qt": 2.0, "preco": 2.45, "doc": "FCL-LX226/018398", "data": "2026-02-26", "lote": "0250620020123", "val": "2029-12-29", "desc": "Oregaos Folha Uli Pet 160 Gr"}], "3563": [{"qt": 3.0, "preco": 18.99, "doc": "FCL-LX226/018398", "data": "2026-02-26", "lote": "9252460030001", "val": "2029-12-31", "desc": "Pimenta Branca Moida Uli Pet 910 Gr"}], "3580": [{"qt": 3.0, "preco": 7.55, "doc": "FCL-LX226/018398", "data": "2026-02-26", "lote": "0242840010009", "val": "2029-12-31", "desc": "Acafrao Das Indias Uli Pet 910"}], "4169": [{"qt": 1.0, "preco": 11.79, "doc": "FCL-LS225/103886", "data": "2025-10-03", "lote": "25032026", "val": "2026-03-25", "desc": "Ketchup Heinz Doses 200X10 ml"}], "4173": [{"qt": 1.0, "preco": 20.39, "doc": "FCL-LS225/103886", "data": "2025-10-03", "lote": "5175", "val": "2026-06-24", "desc": "Maionese Heinz Doses 200x10 ml"}], "4188": [{"qt": 1.0, "preco": 14.85, "doc": "FCL-LS225/103886", "data": "2025-10-03", "lote": "5204", "val": "2026-06-23", "desc": "Mostarda Heinz Doses 200x10 ml"}], "4786": [{"qt": 1.0, "preco": 22.89, "doc": "FCL-LS225/103886", "data": "2025-10-03", "lote": "5E0395", "val": "2027-02-28", "desc": "Massa Couscous Milaneza Cx 10x1 Kg"}], "4958": [{"qt": 2.0, "preco": 53.49, "doc": "FCL-LS225/123577", "data": "2025-10-24", "lote": "2025155", "val": "2026-06-04", "desc": "Pao S/ Gluten Bridor Cong. 50x45 Gr"}], "5000": [{"qt": 1.0, "preco": 27.45, "doc": "FCL-LS225/103886", "data": "2025-10-03", "lote": "L5219", "val": "2027-08-07", "desc": "Pure Batata Cong.Lutosa 10x1 Kg"}], "5013": [{"qt": 1.0, "preco": 12.7, "doc": "FCL-LS225/103886", "data": "2025-10-03", "lote": "107024107", "val": "2026-04-16", "desc": "Espinafres Folhas 50gr Cong.Uli 4x2.5 Kg"}, {"qt": 1.0, "preco": 12.7, "doc": "FCL-LS225/113801", "data": "2025-10-14", "lote": "107024107", "val": "2026-04-16", "desc": "Espinafres Folhas 50gr Cong.Uli 4x2.5 Kg"}], "5187": [{"qt": 1.0, "preco": 24.89, "doc": "FCL-LS225/103886", "data": "2025-10-03", "lote": "498015046", "val": "2027-08-31", "desc": "Cocktail Cogumelos Cong.Ardo 10x600 Gr"}], "5205": [{"qt": 1.0, "preco": 13.39, "doc": "FCL-LX326/021037", "data": "2026-05-13", "lote": "27112025", "val": "2027-11-27", "desc": "Ervilha Saco Neutro Cong. 4x2,5 Kg"}], "5618": [{"qt": 2.0, "preco": 24.95, "doc": "FCL-LS225/112089", "data": "2025-10-11", "lote": "1363", "val": "2026-10-02", "desc": "Pasteis Bacalhau Cong.Mini.Uli Cx 150 Un"}, {"qt": 2.0, "preco": 24.95, "doc": "FCL-LS225/113801", "data": "2025-10-14", "lote": "1363", "val": "2026-10-02", "desc": "Pasteis Bacalhau Cong.Mini.Uli Cx 150 Un"}, {"qt": 3.0, "preco": 24.95, "doc": "FCL-LS225/123577", "data": "2025-10-24", "lote": "1365", "val": "2026-10-03", "desc": "Pasteis Bacalhau Cong.Mini.Uli Cx 150 Un"}, {"qt": 2.0, "preco": 24.69, "doc": "FCL-LS225/162574", "data": "2025-12-10", "lote": "1405", "val": "2026-11-06", "desc": "Pasteis Bacalhau Cong.Mini.Uli Cx 150 Un"}], "5645": [{"qt": 2.0, "preco": 40.59, "doc": "FCL-LX026/021428", "data": "2026-06-02", "lote": "C0126135", "val": "2027-03-27", "desc": "Mix Miniaturas Uli Cong. Cx 4x1 Kg"}, {"qt": 4.0, "preco": 40.59, "doc": "FCL-LX326/027787", "data": "2026-06-12", "lote": "C0126193", "val": "2027-05-06", "desc": "Mix Miniaturas Uli Cong. Cx 4x1 Kg"}], "5653": [{"qt": 2.0, "preco": 33.09, "doc": "FCL-LS225/112089", "data": "2025-10-11", "lote": "2233825", "val": "2026-09-17", "desc": "Rissois Leitao Gr Cong.Uli Cx de 50 Un"}], "5654": [{"qt": 1.0, "preco": 23.89, "doc": "FCL-LS225/113801", "data": "2025-10-14", "lote": "0234025", "val": "2027-04-02", "desc": "Chamucas Grandes Cong.Uli Cx 50 Un"}], "5660": [{"qt": 1.0, "preco": 41.69, "doc": "FCL-LS225/162574", "data": "2025-12-10", "lote": "0244925", "val": "2027-06-05", "desc": "Chamucas Cong.Mini Uli Cx 200 Un"}, {"qt": 1.0, "preco": 41.69, "doc": "FCL-LX026/006314", "data": "2026-04-02", "lote": "0250526", "val": "2027-08-01", "desc": "Chamucas Cong.Mini Uli Cx 200 Un"}, {"qt": 2.0, "preco": 41.69, "doc": "FCL-LX226/057955", "data": "2026-05-06", "lote": "0231526", "val": "2027-10-08", "desc": "Chamucas Cong.Mini Uli Cx 200 Un"}, {"qt": 2.0, "preco": 41.69, "doc": "FCL-LX226/058925", "data": "2026-05-07", "lote": "0211826", "val": "2027-10-27", "desc": "Chamucas Cong.Mini Uli Cx 200 Un"}, {"qt": 2.0, "preco": 41.69, "doc": "FCL-LX226/060082", "data": "2026-05-09", "lote": "0231526", "val": "2027-10-08", "desc": "Chamucas Cong.Mini Uli Cx 200 Un"}, {"qt": 1.0, "preco": 41.69, "doc": "FCL-LX326/021037", "data": "2026-05-13", "lote": "0231526", "val": "2027-10-08", "desc": "Chamucas Cong.Mini Uli Cx 200 Un"}], "5670": [{"qt": 1.0, "preco": 26.89, "doc": "FCL-LS225/113801", "data": "2025-10-14", "lote": "0143925", "val": "2027-03-27", "desc": "Rissois Camarao Mini Uli Cx 200 Un"}, {"qt": 2.0, "preco": 26.89, "doc": "FCL-LS225/123577", "data": "2025-10-24", "lote": "0144125", "val": "2027-04-10", "desc": "Rissois Camarao Mini Uli Cx 200 Un"}, {"qt": 1.0, "preco": 26.89, "doc": "FCL-LS225/162574", "data": "2025-12-10", "lote": "0114125", "val": "2027-04-07", "desc": "Rissois Camarao Mini Uli Cx 200 Un"}, {"qt": 1.0, "preco": 26.89, "doc": "FCL-LX026/006314", "data": "2026-04-02", "lote": "0154925", "val": "2027-05-15", "desc": "Rissois Camarao Mini Uli Cx 200 Un"}], "5671": [{"qt": 2.0, "preco": 26.95, "doc": "FCL-LS225/123577", "data": "2025-10-24", "lote": "2544125", "val": "2027-04-10", "desc": "Croquetes Carne Mini Uli Cx 200 Un"}, {"qt": 1.0, "preco": 26.69, "doc": "FCL-LS225/162574", "data": "2025-12-10", "lote": "2544125", "val": "2027-04-10", "desc": "Croquetes Carne Mini Uli Cx 200 Un"}, {"qt": 1.0, "preco": 26.69, "doc": "FCL-LX026/006314", "data": "2026-04-02", "lote": "2525125", "val": "2027-06-17", "desc": "Croquetes Carne Mini Uli Cx 200 Un"}, {"qt": 3.0, "preco": 26.69, "doc": "FCL-LX226/057955", "data": "2026-05-06", "lote": "2521026", "val": "2027-09-02", "desc": "Croquetes Carne Mini Uli Cx 200 Un"}], "6310": [{"qt": 3.0, "preco": 16.39, "doc": "FCL-LS225/103886", "data": "2025-10-03", "lote": "19H1818F", "val": "2025-12-28", "desc": "Qj.Tipo Feta Cubos Balde 1.8 Kg"}], "6341": [{"qt": 4.0, "preco": 5.99, "doc": "FCL-LX026/002598", "data": "2026-03-24", "lote": "290626", "val": "2026-06-29", "desc": "Leite Uht Magro Gresso 6x1 L"}], "6370": [{"qt": 2.0, "preco": 7.29, "doc": "FCL-LX026/002598", "data": "2026-03-24", "lote": "220726", "val": "2026-07-22", "desc": "Leite Uht Gordo Gresso 6x1 Lt"}], "7019": [{"qt": 3.0, "preco": 8.39, "doc": "FCL-LX226/051234", "data": "2026-04-22", "lote": "40205526", "val": "2026-05-28", "desc": "Qj.Ricota Fresco 1,5 Kg"}], "7668": [{"qt": 3.0, "preco": 4.35, "doc": "FCL-LS225/103886", "data": "2025-10-03", "lote": "013625", "val": "2026-09-28", "desc": "Quinoa Branca SC 1 Kg"}], "7700": [{"qt": 3.0, "preco": 8.49, "doc": "FCL-LX226/051234", "data": "2026-04-22", "lote": "C2604141", "val": "2026-05-19", "desc": "Iogurte Natural Balde 3,5Kg"}, {"qt": 4.0, "preco": 8.49, "doc": "FCL-LS326/014517", "data": "2026-05-18", "lote": "C2605011", "val": "2026-06-05", "desc": "Iogurte Natural Balde 3,5Kg"}], "7771": [{"qt": 10.0, "preco": 6.99, "doc": "FCL-LS225/109564", "data": "2025-10-09", "lote": "25398265", "val": "2026-01-20", "desc": "Presunto Fatiado Uli 500 Gr"}], "8151": [{"qt": 2.0, "preco": 29.9, "doc": "FCL-LS225/112089", "data": "2025-10-11", "lote": "T21225AA", "val": "2027-03-30", "desc": "Pescada Cozer Nº 2 Cong.Uli Cx 5 Kg"}], "8656": [{"qt": 2.0, "preco": 2.75, "doc": "FCL-LS225/103886", "data": "2025-10-03", "lote": "263525", "val": "2026-06-28", "desc": "Sementes Girassol Uli Sc 1 Kg"}], "8657": [{"qt": 3.0, "preco": 2.75, "doc": "FCL-LS225/103886", "data": "2025-10-03", "lote": "142925", "val": "2026-05-28", "desc": "Sementes Linhaca Castanha Uli Sc 1 Kg"}], "8663": [{"qt": 10.0, "preco": 15.59, "doc": "FCL-LX026/002598", "data": "2026-03-24", "lote": "5T31AQ17", "val": "2027-01-31", "desc": "Leite Coco Uli Lt 12x400 Ml"}, {"qt": -9.0, "preco": 15.59, "doc": "NCC-LX026/001755", "data": "2026-03-30", "lote": "5T31AQ17", "val": "2027-01-31", "desc": "Leite Coco Uli Lt 12x400 Ml"}], "8685": [{"qt": 6.0, "preco": 17.25, "doc": "FCL-LS225/109564", "data": "2025-10-09", "lote": "5228133", "val": "2026-08-11", "desc": "Oleo Alimentar Uli 10 Lt"}], "8785": [{"qt": 1.0, "preco": 36.85, "doc": "FCL-LX026/004901", "data": "2026-03-28", "lote": "5266", "val": "2027-03-17", "desc": "Frango Asas Marinadas Cong.Eurof.Cx5x1Kg"}], "8874": [{"qt": 2.0, "preco": 15.89, "doc": "FCL-LS225/147006", "data": "2025-11-21", "lote": "425100901", "val": "2026-10-09", "desc": "Pao Bolo Caco Beterraba Cong.25x120 Gr"}, {"qt": 2.0, "preco": 16.39, "doc": "FCL-LX026/006314", "data": "2026-04-02", "lote": "426022601", "val": "2027-02-26", "desc": "Pao Bolo Caco Beterraba Cong.25x120 Gr"}, {"qt": 1.0, "preco": 16.39, "doc": "FCL-LX026/021428", "data": "2026-06-02", "lote": "426041601", "val": "2027-04-16", "desc": "Pao Bolo Caco Beterraba Cong.25x120 Gr"}], "8946": [{"qt": 10.0, "preco": 6.19, "doc": "FCL-LX026/003705", "data": "2026-03-26", "lote": "9308415", "val": "2026-04-13", "desc": "Fiambre Peito Peru Fatiado Uli 3x250 Gr"}, {"qt": 10.0, "preco": 6.19, "doc": "FCL-LS326/014517", "data": "2026-05-18", "lote": "9310462", "val": "2026-06-09", "desc": "Fiambre Peito Peru Fatiado Uli 3x250 Gr"}], "9111": [{"qt": 2.0, "preco": 5.69, "doc": "FCL-LS225/156661", "data": "2025-12-03", "lote": "L25227296", "val": "2030-12-31", "desc": "Vinho Tinto 13º P.Convento Bag Box 5 Lt"}], "9864": [{"qt": 3.0, "preco": 27.49, "doc": "FCL-LS225/103886", "data": "2025-10-03", "lote": "2266S", "val": "2026-03-23", "desc": "Quiches Peq.Sortidas Cong.Cx 40Un+/-90Gr"}, {"qt": 3.0, "preco": 28.45, "doc": "FCL-LX226/015943", "data": "2026-02-24", "lote": "5016S", "val": "2026-07-16", "desc": "Quiches Peq.Sortidas Cong.Cx 40Un+/-90Gr"}, {"qt": 5.0, "preco": 28.45, "doc": "FCL-LX026/006314", "data": "2026-04-02", "lote": "2034S", "val": "2026-08-03", "desc": "Quiches Peq.Sortidas Cong.Cx 40Un+/-90Gr"}, {"qt": 4.0, "preco": 28.45, "doc": "FCL-LX226/058925", "data": "2026-05-07", "lote": "3070S", "val": "2026-09-11", "desc": "Quiches Peq.Sortidas Cong.Cx 40Un+/-90Gr"}, {"qt": 1.0, "preco": 28.45, "doc": "FCL-LX326/021037", "data": "2026-05-13", "lote": "4078S", "val": "2026-09-19", "desc": "Quiches Peq.Sortidas Cong.Cx 40Un+/-90Gr"}], "9882": [{"qt": 1.0, "preco": 10.75, "doc": "FCL-LS225/103886", "data": "2025-10-03", "lote": "5240", "val": "2026-08-31", "desc": "Flocos Aveia Cimarron 6x1 Kg"}]}